Workbook

Sheet 输入快照
A1: 输入快照（黄色单元格为材料原值，其余表用公式引用）
A3: 项目 | B3: 数值 | C3: 单位 | D3: 来源编号 | E3: 说明
A4: 审阅时点 | B4: 2026-09-10 14:20 | D4: B01 | E4: 交易日未收盘
A5: 基准货币 | B5: 人民币 | D5: B01
A6: 即期汇率(人民币/港币) | B6: 0.92 | C6: RMB/HKD | D6: K02 | E6: 当前即期
A7: 人民币可用现金 | B7: 220000 | C7: RMB | D7: K01 | E7: 未冻结
A8: 港币可用现金 | B8: 60000 | C8: HKD | D8: K02 | E8: 需换汇方可买A股
A9: 冻结申购款 | B9: 16000 | C9: RMB | D9: K03 | E9: 9/12解冻(周末),下一交易日可用
A10: 券商显示总资产 | B10: 1009200 | C10: RMB | D10: K04 | E10: 勾稽锚
A11: A现价 | B11: 49.5 | C11: RMB | D11: H01/M01
A12: A持仓 | B12: 8000 | C12: 股 | D12: H01 | E12: 可卖6000;2000当日买入T+1
A13: B现价(9/9收盘) | B13: 120 | C13: RMB | D13: H02/M02 | E13: 9/10停牌,不可成交
A14: B持仓 | B14: 1800 | C14: 股 | D14: H02/CA01 | E14: 10转5后
A15: C现价(跌停) | B15: 60 | C15: RMB | D15: H03/M03 | E15: 14:20买一无有效挂单
A16: C持仓 | B16: 1000 | C16: 股 | D16: H03
A17: D现价 | B17: 10 | C17: HKD | D17: H04/M04 | E17: 跨境ETF,T+0
A18: D持仓 | B18: 5000 | C18: 份 | D18: H04
A20: 批次成本重建
A21: 批次 | B21: 数量 | C21: 价格 | D21: 费用 | E21: 成交日汇率 | F21: 成本(RMB)
A22: A-L01 | B22: 4000 | C22: 45 | D22: 225 | E22: — | F22: =B22*C22+D22
A23: A-L02 | B23: 2000 | C23: 50 | D23: 100 | E23: — | F23: =B23*C23+D23
A24: A-L03 | B24: 2000 | C24: 52 | D24: 104 | E24: — | F24: =B24*C24+D24
A25: B-L04 | B25: 1200 | C25: 150 | D25: 360 | E25: — | F25: =B25*C25+D25
A26: C-L05 | B26: 1000 | C26: 68 | D26: 102 | E26: — | F26: =B26*C26+D26
A27: D-L06 | B27: 3000 | C27: 11.6 | D27: 34.8 | E27: 0.94 | F27: =(B27*C27+D27)*E27
A28: D-L07 | B28: 2000 | C28: 10.8 | D28: 21.6 | E28: 0.93 | F28: =(B28*C28+D28)*E28

Sheet 持仓勾稽
A1: 持仓勾稽与盈亏（公式引用输入快照）
A3: 项目 | B3: 数量 | C3: 现价 | D3: 成本(RMB) | E3: 市值(RMB) | F3: 未实现盈亏(RMB) | G3: 权重% | H3: 备注
A4: 铜资源股A | B4: =输入快照!B12 | C4: =输入快照!B11 | D4: =SUM(输入快照!F22:F24) | E4: =B4*C4 | F4: =E4-D4 | G4: =E4/持仓勾稽!E12 | H4: 可卖6000;2000当日T+1
A5: 光模块股B | B5: =输入快照!B14 | C5: =输入快照!B13 | D5: =输入快照!F25 | E5: =B5*C5 | F5: =E5-D5 | G5: =E5/持仓勾稽!E12 | H5: 停牌,价为9/9收盘
A6: 新能源股C | B6: =输入快照!B16 | C6: =输入快照!B15 | D6: =输入快照!F26 | E6: =B6*C6 | F6: =E6-D6 | G6: =E6/持仓勾稽!E12 | H6: 跌停
A7: 恒生科技ETF D | B7: =输入快照!B18 | C7: =输入快照!B17*输入快照!B6 | D7: =SUM(输入快照!F27:F28) | E7: =B7*C7 | F7: =E7-D7 | G7: =E7/持仓勾稽!E12 | H7: HKD价×即期汇率
A8: 证券市值合计 | E8: =SUM(E4:E7)
A9: 人民币现金 | E9: =输入快照!B7
A10: 港币现金折RMB | E10: =输入快照!B8*输入快照!B6
A11: 冻结申购款 | E11: =输入快照!B9
A12: 总资产(计算) | E12: =E8+E9+E10+E11
A13: 券商显示总资产 | E13: =输入快照!B10
A14: 勾稽残差 | E14: =E13-E12
A16: 注: 权重%分母=计算总资产; 港币成本按成交日汇率(L06 0.94,L07 0.93), D市值按当前即期0.92

Sheet 交易日历
A1: 交易日历（as-of 2026-09-10 周四 14:20）
A3: 日历日 | B3: 星期 | C3: 是否交易日 | D3: 可执行时段 | E3: 资金可用/可划转 | F3: 备注
A4: 2026-09-10 | B4: 周四 | C4: 是 | D4: 14:20-15:00 仍可交易 | E4: A可卖6000; B停牌; C跌停可报未必成; D T+0 | F4: 审阅时点
A5: 2026-09-11 | B5: 周五 | C5: 是 | D5: 全天 | E5: A当日2000股解冻为可卖; C若开板可成交 | F5: 计划D1
A6: 2026-09-12 | B6: 周六 | C6: 否 | D6: 休市 | F6: 冻结款预计解冻日(非交易日)
A7: 2026-09-13 | B7: 周日 | C7: 否 | D7: 休市
A8: 2026-09-14 | B8: 周一 | C8: 是 | D8: 全天 | E8: 16000冻结款解冻可用; B仍可能停牌 | F8: 计划D2
A9: 2026-09-15 | B9: 周二 | C9: 是 | D9: 全天 | F9: 计划D3
A10: 2026-09-17 | B10: 周四 | C10: 是 | D10: 全天 | E10: B停牌预计≤5交易日,约此日前复牌 | F10: B复牌观察日

Sheet 硬约束状态
A1: 硬约束状态表（当前 vs 主方案交易后）
A3: 约束 | B3: 阈值 | C3: 当前值 | D3: 主方案后值 | E3: 判定 | F3: 反解达标量 | G3: 对应规则
A4: 风险资产仓位 | B4: ≤70% | C4: ='持仓勾稽'!E8/持仓勾稽!E12 | D4: =方案对比!C10 | E4: 主方案后42.5%
A5: 单票A | B5: ≤22% | C5: ='持仓勾稽'!E4/持仓勾稽!E12 | D5: =方案对比!C8 | E5: 至少卖A 3600股(整手) | F5: R1
A6: 单票B | B6: ≤22% | C6: ='持仓勾稽'!E5/持仓勾稽!E12 | D6: =方案对比!C9 | E6: 停牌无法卖;监控123.30 | F6: R4
A7: 主题B+C+D | B7: ≤35% | C7: =('持仓勾稽'!E5+'持仓勾稽'!E6+'持仓勾稽'!E7)/持仓勾稽!E12 | D7: =方案对比!C11 | E7: 主方案后21.4%
A8: 外币敞口 | B8: ≤25% | C8: =('持仓勾稽'!E7+'持仓勾稽'!E10)/持仓勾稽!E12 | D8: =方案对比!C12 | E8: 10%,不绑定
A9: 自由现金 | B9: ≥25% | C9: =('持仓勾稽'!E9+'持仓勾稽'!E10)/持仓勾稽!E12 | D9: =方案对比!C13 | E9: 主方案后55.9%
A10: 一周压力损失 | B10: ≤6% | C10: =方案对比!B14 | D10: =方案对比!C15 | E10: 卖C+D替代多卖A | F10: R2/R3

Sheet 方案对比
A1: 方案对比（未调整 / 主方案合规 / C卖不出的备用路径）
A3: 指标 | B3: 未调整 | C3: 主方案(A3700+C1000+D5000) | D3: 备用(C0: A4800+D5000)
A4: 卖出A(股) | B4: 0 | C4: 3700 | D4: 4800
A5: 卖出C(股) | B5: 0 | C5: 1000 | D5: 0
A6: 卖出D(份) | B6: 0 | C6: 5000 | D6: 5000
A7: 总资产(RMB) | B7: 1009200 | C7: 1008786 | D7: 1008790
A8: A权重 | B8: 0.3924 | C8: 0.211 | D8: 0.157
A9: B权重 | B9: 0.214 | C9: 0.2141 | D9: 0.2141
A10: 风险资产仓位 | B10: 0.7115 | C10: 0.4251 | D10: 0.4306
A11: 主题B+C+D | B11: 0.3191 | C11: 0.2141 | D11: 0.2736
A12: 外币敞口 | B12: 0.1003 | C12: 0.1003 | D12: 0.1003
A13: 自由现金 | B13: 0.2727 | C13: 0.559 | D13: 0.5535
A14: 压力损失率(当前) | B14: 0.0907 | C14: — | D14: —
A15: 压力损失率(方案后) | B15: — | C15: 0.0594 | D15: 0.0589

Sheet 交易明细
A1: 主方案交易明细（成交假设下；费用率为显式假设）
A2: 假设费率: A股卖出 佣金0.10%+印花税0.05%+过户费0.001%=0.151%(最低5元); ETF卖出 0.101%; 无滑点(题未给)。D卖出得港币,换汇前不可买A股。
A4: 规则 | B4: 标的 | C4: 数量 | D4: 价格区间 | E4: 成交额(RMB) | F4: 费用 | G4: 净回笼(RMB) | H4: 实现盈亏(RMB) | I4: 批次/可卖说明
A5: R1 | B5: 卖A | C5: 3700 | D5: 49.00-49.80(限价) | E5: 183150 | F5: 276.6 | G5: 182873.4 | H5: 5075 | I5: 卖可卖批次L01+L02共6000中的3700;L03当日2000受T+1不可卖
A6: R2 | B6: 卖C | C6: 1000 | D6: 60.00跌停价限价;若开板市价优先 | E6: 60000 | F6: 90.6 | G6: 59909.4 | H6: -8193 | I6: 跌停可报单,买盘不足或不成交;未成交转R2b
A7: R3 | B7: 卖D | C7: 5000 | D7: 9.90-10.10港币 | E7: 46000 | F7: 46.5 | G7: 45953.5 | H7: -6899 | I7: T+0;得港币约50000,换汇前不增加A股可用金
A8: 合计 | E8: =SUM(E5:E7) | F8: =SUM(F5:F7) | G8: =SUM(G5:G7) | H8: =SUM(H5:H7)

Sheet 条件规则
A1: if→then 交易纪律（不代客下单,不保证成交）
A3: 规则号 | B3: 触发条件(阈值+时点) | C3: 动作 | D3: 数量/口径 | E3: 目标仓位 | F3: 费用与净回笼 | G3: 执行时点 | H3: 未成交后手 | I3: 交易后复核
A4: R1 | B4: 9/10收盘前A权重>22%(当前39.2%);A在49.00-49.80区间有买盘 | C4: 卖A | D4: 3700股(累计;基准持仓8000) | E4: A权重≤21% | F4: 费用≈277,净回笼≈18.3万 | G4: 9/10 14:30-14:55限价挂单 | H4: 若A封涨停/无买盘未成交,9/11改限价49.50±0.50;仍未成交则下延并先卖D | I4: 复核A权重≤22%、风险资产≤70%
A5: R2 | B5: C仍跌停且买一薄;风险约束要求压损失 | C5: 卖C | D5: 1000股(累计;基准1000,清仓) | E5: C=0 | F5: 费用≈91,净回笼≈6.0万 | G5: 9/10收盘前+9/11开盘 | H5: 若3个交易日仍跌停无法成交,改卖A至4800股(见R2b) | I5: 复核压力损失≤6%
A6: R2b | B6: C连续3日跌停无法成交 | C6: 追加卖A | D6: +1100股(累计A卖4800) | E6: A权重≤16% | F6: 费用增量≈82 | G6: 9/14 | H6: 用A替代C承担压降 | I6: 复核压力损失≤6%
A7: R3 | B7: D现价≥9.90港币且需降风险 | C7: 卖D | D7: 5000份(累计;基准5000,清仓) | E7: D=0 | F7: 费用≈46,得港币≈5万 | G7: 9/10-9/11 T+0随时 | H7: 若D跌穿9.80支撑,改为限价9.80-10.00;不急于在低位砸出 | I7: 复核外币敞口仍≤25%
A8: R4 | B8: B复牌且报价>123.30(权重将破22%) | C8: 评估减B | D8: 按整手反解 | E8: B权重≤21% | F8: — | G8: 复牌首日盘中 | H8: 停牌期间不可执行;复牌若>123.30须卖至21%以下;若复牌<112支撑不追卖 | I8: 复核B权重、相关性聚集
A9: R5(止损/止盈) | B9: A跌破近端支撑46.80且放量 | C9: 不补仓/不加杠杆;已减仓部分持有观察 | D9: — | E9: 维持A≤21% | F9: — | G9: 盘中 | H9: 跌破46.80不做T不加仓;反弹至52.00压力且权重回升,再减500股 | I9: 禁止在约束未回限内加仓
A10: R6(撤销) | B10: 客户书面放宽单票上限或压力损失阈值 | C10: 暂停R1-R3 | D10: — | E10: — | F10: — | G10: — | H10: 新约束下重算;否则规则持续有效 | I10: 以最新书面约束为准

Sheet 核验结果
A1: 交付自检回执
A3: 自检项 | B3: 填写值
A4: 交付清单 | B4: 1件: 组合诊断与交易计划.xlsx (本文件),8个工作表
A5: 工作簿可复算 | B5: 持仓勾稽!E4='输入快照'!B14*'输入快照'!B11 等公式;批次成本F列=(B*C+D)*E;重算见 LibreOffice
A6: 占比分母 | B6: 所有权重分母=计算总资产=1,008,926(交易前1,009,200);分子为对应市值
A7: 最紧约束 | B7: 单票A:当前39.24%>22%;反解卖A 3600股(整手);主方案卖3700股留缓冲→规则R1
A8: 分解型占比 | B8: A+B+C+D+现金+冻结=100.00%;主题B+C+D主方案21.41%
A9: 最不利情景 | B9: S01一周统一冲击:方案后损失59,965=5.94%≤6%(取最不利;B停牌15%无法降)
A10: 日期来源 | B10: 动作日均取自交易日历表;9/12-13周末非交易日,冻结款9/14可用
A11: 数量口径 | B11: R1累计卖3700股(基准8000);R2b累计卖4800股;不混用追加/累计
A12: 费用口径 | B12: A股0.151%、ETF0.101%(题未给,显式假设);隐含费率与假设一致
A13: 跨文件一致 | B13: 正文A权重21.10%=方案对比!C8=交易明细R1;压力损失5.94%=方案对比!C15
