Workbook

Sheet 原始账户记录
A1: 字段 | B1: 数值 | C1: 币种或单位 | D1: 记录时间 | E1: 来源
A2: 证券市值小计 | B2: 869820 | C2: 人民币元 | D2: 2026-08-14 15:05 | E2: 托管系统
A3: 人民币可用现金 | B3: 142500 | C3: 人民币元 | D3: 2026-08-14 15:05 | E3: 资金系统
A4: 美元现金 | B4: 3000 | C4: 美元 | D4: 2026-08-14 15:05 | E4: 资金系统
A5: 美元兑人民币折算汇率 | B5: 7.18 | C5: 人民币/美元 | D5: 2026-08-14 15:00 | E5: 内部估值表
A6: 待扣费用 | B6: 1200 | C6: 人民币元 | D6: 2026-08-14 15:05 | E6: 托管系统
A7: 账户总资产记录 | B7: 1032660 | C7: 人民币元 | D7: 2026-08-14 15:05 | E7: 托管系统
A8: 组合经理手工记录总资产 | B8: 1029000 | C8: 人民币元 | D8: 2026-08-14 15:10 | E8: 组合工作表
A9: 本周计划净流出 | B9: 50000 | C9: 人民币元 | D9: 2026-08-17 | E9: 客户已确认
A11: 核对项目 | B11: 公式/数值 | C11: 结论
A12: 明细净资产 | B12: =B2+B3+B4*B5-B6 | C12: 证券市值+人民币现金+美元折算-待扣费
A13: 与托管总资产差额 | B13: =B11-B7 | C13: 应为0，托管记录可与明细勾稽
A14: 与经理手工记录差额 | B14: =B11-B8 | C14: 3,660元，来源附件未解释；不得静默择一或补造资产
A15: 采用口径 | B15: =B11 | C15: 客观测算以可勾稽明细/托管1,032,660元为主，同时披露手工口径1,029,000元及指标区间

Sheet 原始持仓记录
A1: 证券ID | B1: 证券类型 | C1: 行业或主题 | D1: 批次日期 | E1: 数量 | F1: 单位成本 | G1: 成本币种 | H1: 是否当日买入 | I1: 当前价格 | J1: 价格币种 | K1: 可卖数量 | L1: 交易状态 | M1: 涨跌停状态 | N1: 最小交易单位 | O1: ADV20万元 | P1: 备注
A2: P01 | B2: A股 | C2: 电子 | D2: 2026-05-10 | E2: 2500 | F2: 43.2 | G2: 人民币 | H2: 否 | I2: 32.8 | J2: 人民币 | K2: 2500 | L2: 正常 | M2: 无 | N2: 100 | O2: 8600
A3: P01 | B3: A股 | C3: 电子 | D3: 2026-07-02 | E3: 1500 | F3: 37.5 | G3: 人民币 | H3: 否 | I3: 32.8 | J3: 人民币 | K3: 1500 | L3: 正常 | M3: 无 | N3: 100 | O3: 8600
A4: P01 | B4: A股 | C4: 电子 | D4: 2026-08-14 | E4: 1000 | F4: 31.9 | G4: 人民币 | H4: 是 | I4: 32.8 | J4: 人民币 | K4: 0 | L4: 正常 | M4: 无 | N4: 100 | O4: 8600 | P4: T+1不可卖
A5: P02 | B5: A股 | C5: 计算机 | D5: 2026-03-18 | E5: 3000 | F5: 54.2 | G5: 人民币 | H5: 否 | I5: 58.4 | J5: 人民币 | K5: 3000 | L5: 正常 | M5: 跌停 | N5: 100 | O5: 2100 | P5: 收盘封单，次日成交不确定
A6: P03 | B6: A股 | C6: 医药 | D6: 2026-04-11 | E6: 8000 | F6: 10.3 | G6: 人民币 | H6: 否 | I6: 9.62 | J6: 人民币 | K6: 8000 | L6: 正常 | M6: 无 | N6: 100 | O6: 4700
A7: P04 | B7: A股 | C7: 工业 | D7: 2026-01-20 | E7: 6000 | F7: 11.9 | G7: 人民币 | H7: 否 | I7: 12.35 | J7: 人民币 | K7: 0 | L7: 停牌 | M7: 不适用 | N7: 100 | O7: 900 | P7: 价格为8/13，复牌日未知
A8: P05 | B8: A股 | C8: 计算机 | D8: 2025-12-05 | E8: 2000 | F8: 82.4 | G8: 人民币 | H8: 否 | I8: 105 | J8: 人民币 | K8: 2000 | L8: 正常 | M8: 无 | N8: 100 | O8: 12800 | P8: 经理看好意见未获风险例外
A9: P06 | B9: 境内ETF | C9: 红利 | D9: 2026-02-06 | E9: 10000 | F9: 3.1 | G9: 人民币 | H9: 否 | I9: 2.88 | J9: 人民币 | K9: 10000 | L9: 正常 | M9: 无 | N9: 100 | O9: 56000 | P9: 8/12每份现金分配0.80元；用调整后参考价
A10: P07 | B10: 港股ETF | C10: 海外科技 | D10: 2026-06-16 | E10: 10000 | F10: 16.4 | G10: 港币 | H10: 否 | I10: 15.3 | J10: 港币 | K10: 10000 | L10: 正常 | M10: 无 | N10: 500 | O10: 12500 | P10: 估值汇率0.92人民币/港币

Sheet 持仓诊断
A1: 证券ID | B1: 批次日期 | C1: 数量 | D1: 可卖数量 | E1: 成本人民币 | F1: 市值人民币 | G1: 浮动盈亏 | H1: 主NAV权重 | I1: 手工NAV权重 | J1: 行业/主题 | K1: 风险等级 | L1: 外币暴露人民币 | M1: 状态说明
A2: P01 | B2: 2026-05-10 | C2: 2500 | D2: 2500 | E2: ='原始持仓记录'!E2*'原始持仓记录'!F2*1 | F2: ='原始持仓记录'!E2*'原始持仓记录'!I2*1 | G2: =F2-E2 | H2: =F2/'原始账户记录'!$B$14 | I2: =F2/'原始账户记录'!$B$8 | J2: 科技 | K2: 高 | L2: =IF(A2="P07",F2,0)
A3: P01 | B3: 2026-07-02 | C3: 1500 | D3: 1500 | E3: ='原始持仓记录'!E3*'原始持仓记录'!F3*1 | F3: ='原始持仓记录'!E3*'原始持仓记录'!I3*1 | G3: =F3-E3 | H3: =F3/'原始账户记录'!$B$14 | I3: =F3/'原始账户记录'!$B$8 | J3: 科技 | K3: 高 | L3: =IF(A3="P07",F3,0)
A4: P01 | B4: 2026-08-14 | C4: 1000 | D4: 0 | E4: ='原始持仓记录'!E4*'原始持仓记录'!F4*1 | F4: ='原始持仓记录'!E4*'原始持仓记录'!I4*1 | G4: =F4-E4 | H4: =F4/'原始账户记录'!$B$14 | I4: =F4/'原始账户记录'!$B$8 | J4: 科技 | K4: 高 | L4: =IF(A4="P07",F4,0) | M4: T+1不可卖
A5: P02 | B5: 2026-03-18 | C5: 3000 | D5: 3000 | E5: ='原始持仓记录'!E5*'原始持仓记录'!F5*1 | F5: ='原始持仓记录'!E5*'原始持仓记录'!I5*1 | G5: =F5-E5 | H5: =F5/'原始账户记录'!$B$14 | I5: =F5/'原始账户记录'!$B$8 | J5: 科技 | K5: 高 | L5: =IF(A5="P07",F5,0) | M5: 收盘封单，次日成交不确定
A6: P03 | B6: 2026-04-11 | C6: 8000 | D6: 8000 | E6: ='原始持仓记录'!E6*'原始持仓记录'!F6*1 | F6: ='原始持仓记录'!E6*'原始持仓记录'!I6*1 | G6: =F6-E6 | H6: =F6/'原始账户记录'!$B$14 | I6: =F6/'原始账户记录'!$B$8 | J6: 医药 | K6: 中 | L6: =IF(A6="P07",F6,0)
A7: P04 | B7: 2026-01-20 | C7: 6000 | D7: 0 | E7: ='原始持仓记录'!E7*'原始持仓记录'!F7*1 | F7: ='原始持仓记录'!E7*'原始持仓记录'!I7*1 | G7: =F7-E7 | H7: =F7/'原始账户记录'!$B$14 | I7: =F7/'原始账户记录'!$B$8 | J7: 工业 | K7: 中 | L7: =IF(A7="P07",F7,0) | M7: 价格为8/13，复牌日未知
A8: P05 | B8: 2025-12-05 | C8: 2000 | D8: 2000 | E8: ='原始持仓记录'!E8*'原始持仓记录'!F8*1 | F8: ='原始持仓记录'!E8*'原始持仓记录'!I8*1 | G8: =F8-E8 | H8: =F8/'原始账户记录'!$B$14 | I8: =F8/'原始账户记录'!$B$8 | J8: 科技 | K8: 高 | L8: =IF(A8="P07",F8,0) | M8: 经理看好意见未获风险例外
A9: P06 | B9: 2026-02-06 | C9: 10000 | D9: 10000 | E9: ='原始持仓记录'!E9*'原始持仓记录'!F9*1 | F9: ='原始持仓记录'!E9*'原始持仓记录'!I9*1 | G9: =F9-E9 | H9: =F9/'原始账户记录'!$B$14 | I9: =F9/'原始账户记录'!$B$8 | J9: 红利 | K9: 低 | L9: =IF(A9="P07",F9,0) | M9: 8/12每份现金分配0.80元；用调整后参考价
A10: P07 | B10: 2026-06-16 | C10: 10000 | D10: 10000 | E10: ='原始持仓记录'!E10*'原始持仓记录'!F10*0.92 | F10: ='原始持仓记录'!E10*'原始持仓记录'!I10*0.92 | G10: =F10-E10 | H10: =F10/'原始账户记录'!$B$14 | I10: =F10/'原始账户记录'!$B$8 | J10: 科技 | K10: 中高 | L10: =IF(A10="P07",F10,0) | M10: 估值汇率0.92人民币/港币
A11: 合计 | C11: =SUM(C2:C10) | D11: =SUM(D2:D10) | E11: =SUM(E2:E10) | F11: =SUM(F2:F10) | G11: =SUM(G2:G10) | H11: =SUM(H2:H10) | L11: =SUM(L2:L10)

Sheet 约束复核
A1: 阶段 | B1: 指标 | C1: 实际值（主口径） | D1: 手工口径/保守值 | E1: 阈值 | F1: 状态 | G1: 解释
A2: 转出前 | B2: 单一证券最大权重 | C2: =MAX(SUMIF(持仓诊断!A:A,"P01",持仓诊断!F:F),SUMIF(持仓诊断!A:A,"P02",持仓诊断!F:F),SUMIF(持仓诊断!A:A,"P03",持仓诊断!F:F),SUMIF(持仓诊断!A:A,"P04",持仓诊断!F:F),SUMIF(持仓诊断!A:A,"P05",持仓诊断!F:F),SUMIF(持仓诊断!A:A,"P06",持仓诊断!F:F),SUMIF(持仓诊断!A:A,"P07",持仓诊断!F:F))/1032660 | D2: =C2*1032660/1029000 | E2: 0.2 | F2: =IF(MAX(C2:D2)<=E2,"通过",IF(MIN(C2:D2)>E2,"不通过","边界")) | G2: P05约20.33%–20.41%，超限
A3: 转出前 | B3: 科技主题 | C3: =SUMIF(持仓诊断!J:J,"科技",持仓诊断!F:F)/1032660 | D3: =C3*1032660/1029000 | E3: 0.4 | F3: =IF(C3<=E3,"通过","不通过") | G3: P01+P02+P05+P07
A4: 转出前 | B4: 高风险 | C4: =SUMIF(持仓诊断!K:K,"高",持仓诊断!F:F)/1032660 | D4: =C4*1032660/1029000 | E4: 0.45 | F4: =IF(C4<=E4,"通过","不通过") | G4: P01+P02+P05
A5: 转出前 | B5: 外币资产 | C5: =SUM(持仓诊断!L:L)/1032660 | D5: =C5*1032660/1029000 | E5: 0.15 | F5: =IF(MAX(C5:D5)<=E5,"通过","不通过") | G5: P07按0.92折算
A6: 转出后 | B6: 现金比例（含美元现金净额） | C6: =(142500-50000+3000*7.18-1200)/(1032660-50000) | D6: =(142500-50000)/(1032660-50000) | E6: 0.1 | F6: =IF(C6>=E6,"通过（宽口径）/人民币现金口径不通过","不通过") | G6: 宽口径11.48%；仅人民币现金9.41%，现金类定义需确认
A7: 转出后 | B7: 科技主题 | C7: =SUMIF(持仓诊断!J:J,"科技",持仓诊断!F:F)/(1032660-50000) | D7: =SUMIF(持仓诊断!J:J,"科技",持仓诊断!F:F)/(1029000-50000) | E7: 0.4 | F7: =IF(C7<=E7,"通过","不通过") | G7: 转出降低分母，恶化至约70.2%
A8: 转出后 | B8: 高风险 | C8: =SUMIF(持仓诊断!K:K,"高",持仓诊断!F:F)/(1032660-50000) | D8: =SUMIF(持仓诊断!K:K,"高",持仓诊断!F:F)/(1029000-50000) | E8: 0.45 | F8: =IF(C8<=E8,"通过","不通过") | G8: 约55.9%
A9: 转出后 | B9: 外币资产 | C9: =SUM(持仓诊断!L:L)/(1032660-50000) | D9: =SUM(持仓诊断!L:L)/(1029000-50000) | E9: 0.15 | F9: =IF(MAX(C9:D9)<=E9,"通过","不通过") | G9: 约14.32%–14.37%，接近上限

Sheet 调整纪律
A1: 规则ID | B1: 阶段 | C1: if条件 | D1: then动作 | E1: 拟卖数量 | F1: 参考价 | G1: 估计费用 | H1: 净回款 | I1: 交易后持仓 | J1: 交易后主NAV | K1: 单股最大 | L1: 科技主题 | M1: 高风险 | N1: 外币 | O1: 现金比例 | P1: 失效条件/复核
A2: A01 | B2: 8/17转出前 | C2: 若人民币现金足以完成已确认的50,000元转出 | D2: 则保留50,000元并完成资金安排；不将拟卖未成交款计入现金 | E2: 0 | F2: 0 | G2: 0 | H2: 0 | I2: 原持仓 | J2: 982660 | O2: =(142500-50000+21540-1200)/982660 | P2: 资金系统显示不足则暂停转出并复核
A3: A02 | B3: 正常成交 | C3: 若P05报价有效、可卖2,000股且盘口正常 | D3: 则提交卖出P05 2,000股的审批；经理看好意见不是风险例外 | E3: 2000 | F3: 105 | G3: =MAX(5,E3*F3*0.03%)+E3*F3*0.05% | H3: =E3*F3-G3 | I3: P05=0 | J3: =J2-G3 | K3: =MAX(175200,164000,140760)/(J3) | L3: =(689960-E3*F3)/J3 | M3: =(549200-E3*F3)/J3 | N3: =140760/J3 | O3: =((142500-50000+21540-1200)+H3)/J3 | P3: 报价/可卖数无效则不执行
A4: A03 | B4: 正常成交 | C4: 若A02成交且P01在下周一全部5,000股已可卖、报价有效 | D4: 则提交卖出P01 2,800股的审批，优先分配旧批次；100股整数 | E4: 2800 | F4: 32.8 | G4: =MAX(5,E4*F4*0.03%)+E4*F4*0.05% | H4: =E4*F4-G4 | I4: P01余2,200股 | J4: =J3-G4 | K4: =MAX(175200,72000,140760)/J4 | L4: =(689960-E3*F3-E4*F4)/J4 | M4: =(549200-E3*F3-E4*F4)/J4 | N4: =140760/J4 | O4: =((142500-50000+21540-1200)+H3+H4)/J4 | P4: 若P01当日买入批次未解冻或深度不足则只卖可卖旧批次并重算
A5: A04 | B5: P02跌停 | C5: 若P02仍跌停封单或无有效买盘 | D5: 则条件未成立，因此未执行P02卖出；不把委托计入现金 | E5: 0 | F5: 58.4 | G5: 0 | H5: 0 | I5: P02保持3,000股 | J5: =J4 | K5: =K4 | L5: =L4 | M5: =M4 | N5: =N4 | O5: =O4 | P5: 涨跌停状态恢复时重新复核
A6: A05 | B6: P04停牌 | C6: 若P04仍停牌 | D6: 则卖出数量记0，不用8/13价格假设可成交 | E6: 0 | F6: 12.35 | G6: 0 | H6: 0 | I6: P04保持6,000股 | J6: =J4 | K6: =K4 | L6: =L4 | M6: =M4 | N6: =N4 | O6: =O4 | P6: 复牌后用新报价和可卖数复核
A7: A06 | B7: 风险继续扩大 | C7: 若转出后任一口径科技>40%、高风险>45%、单股>20%或外币>15% | D7: 则暂停新增风险，按A02/A03或等风险改善改案恢复；不得以回本/长期看好为由拖延 | E7: 0 | F7: 0 | G7: 0 | H7: 0 | I7: 待复核 | J7: =J4 | K7: =K4 | L7: =L4 | M7: =M4 | N7: =N4 | O7: =O4 | P7: 全部硬约束通过后解除
A8: A07 | B8: 现金口径 | C8: 若仅人民币现金/总资产低于10% | D8: 则在转出前保留或变现至少5,766元以上，并以成交回报复算；美元是否属于现金类须确认 | E8: 0 | F8: 0 | G8: 0 | H8: 0 | I8: 不新增证券 | J8: =J4 | K8: =K4 | L8: =L4 | M8: =M4 | N8: =N4 | O8: =O4 | P8: 现金类定义及到账状态明确

Sheet 口径与结论
A1: 主题 | B1: 说明
A2: 结论 | B2: 托管总资产1,032,660元可与明细完全勾稽；组合经理1,029,000元低3,660元，来源未解释。主测算用可勾稽值，同时在约束表保留两口径区间。
A3: 优先级 | B3: 不是按账面盈亏排序。P05先处理，因为单票超20%、高风险且科技集中，且“长期看好”没有风险例外；P01其次，因为高风险/科技且下周一当日买入批次解冻后可卖。P02虽风险高但跌停成交不确定；P04停牌不可作为即时资金来源。
A4: 资金转出 | B4: 转出50,000元后分母下降，单票、科技、高风险和外币比率均上升。宽现金口径（人民币+美元折算-费用）约11.48%通过；仅人民币现金约9.41%不通过，必须确认“现金类资产”定义或预留至少约5,766元。
A5: 推荐条件方案 | B5: 若P05、P01交易条件正常，则拟卖P05 2,000股、P01 2,800股。预计股票卖出费用分别168.00元和73.47元；交易后科技约39.50%、高风险约25.64%、最大单股约17.83%、外币约14.33%，主口径均通过。
A6: 交易边界 | B6: 本工作簿仅为调仓前分析。停牌、跌停、当日买入不可卖均按0可成交处理；没有成交回报不得写成已卖。P06使用除权后2.88元，不把0.80元现金分配机械认定为投资损失。
