Workbook

Sheet 决策摘要
A1: 组合持仓诊断与交易纪律 — 决策摘要
A3: 资料截点 | B3: 2026-08-14 17:00 (北京时间)
A4: 采用总资产口径 | B4: 托管系统底账口径 1,032,660 元 | C4: (组合经理手工记录 1,029,000 元，差异 3,660 元见双口径勾稽表)
A6: 关键指标
A7: 指标 | B7: 调整前 | C7: 转出后(无减仓) | D7: 拟定方案后 | E7: 约束阈值 | F7: 判定
A8: 总资产(元) | B8: =总资产双口径勾稽!B8 | C8: =总资产双口径勾稽!B8-50000 | D8: =调仓方案与交易明细!B21 | E8: — | F8: —
A9: 人民币现金(元) | B9: 142500 | C9: 92500 | D9: =调仓方案与交易明细!B22 | E9: ≥10%总资产 | F9: —
A10: 现金占比 | B10: =142500/总资产双口径勾稽!B8 | C10: =92500/(总资产双口径勾稽!B8-50000) | D10: =调仓方案与交易明细!B23 | E10: ≥10% | F10: —
A11: P05单票权重 | B11: =210000/总资产双口径勾稽!B8 | C11: =210000/(总资产双口径勾稽!B8-50000) | D11: =189000/调仓方案与交易明细!B21 | E11: ≤20% | F11: —
A12: 科技主题权重 | B12: =689960/总资产双口径勾稽!B8 | C12: =689960/(总资产双口径勾稽!B8-50000) | D12: =390440/调仓方案与交易明细!B21 | E12: ≤40% | F12: —
A13: 高风险持仓权重 | B13: =549200/总资产双口径勾稽!B8 | C13: =549200/(总资产双口径勾稽!B8-50000) | D13: =364200/调仓方案与交易明细!B21 | E13: ≤45% | F13: —
A14: 外币资产权重 | B14: =162300/总资产双口径勾稽!B8 | C14: =162300/(总资产双口径勾稽!B8-50000) | D14: =21540/调仓方案与交易明细!B21 | E14: ≤15% | F14: —
A16: 结论与首要动作
A17: 当前组合五项已批准约束全部超限：P05单票20.34%、科技主题66.81%、高风险53.18%、外币15.72%、转出后现金约9.41%。
A18: 最紧约束为科技主题上限40%，需在转出5万元后减持科技类市值约29.7万元；P02跌停、P04停牌不可作为可成交标的。
A19: 拟定方案：8月17日(周一)卖出P07全部10000份、P05 200股、P01 4200股，合计成交约29.95万元，扣费约267.77元，净回笼约29.93万元。
A20: 方案后五项约束全部达标：科技39.74%、高风险37.07%、P05单票19.24%、外币2.19%、现金39.88%。
A21: P05'长期看好暂不减持'为组合经理个人意见，未经客户确认和风险例外审批，不替代已批准上限；本方案仅减持最低必要数量200股。
A22: 本工作簿仅用于调仓前分析，不代表任何交易已下达或执行；实际成交取决于当时买盘与涨跌停状态。

Sheet 原始_账户汇总
A1: 原始数据 — 账户汇总 (来源: 托管系统/资金系统/组合工作表)
A3: 字段 | B3: 数值 | C3: 币种或单位 | D3: 记录时间 | E3: 来源
A4: 证券市值小计 | B4: 869820 | C4: 人民币元 | D4: 2026-08-14 15:05 | E4: 托管系统
A5: 人民币可用现金 | B5: 142500 | C5: 人民币元 | D5: 2026-08-14 15:05 | E5: 资金系统
A6: 美元现金 | B6: 3000 | C6: 美元 | D6: 2026-08-14 15:05 | E6: 资金系统
A7: 美元兑人民币折算汇率 | B7: 7.18 | C7: 人民币/美元 | D7: 2026-08-14 15:00 | E7: 内部估值表
A8: 待扣费用 | B8: 1200 | C8: 人民币元 | D8: 2026-08-14 15:05 | E8: 托管系统
A9: 账户总资产记录 | B9: 1032660 | C9: 人民币元 | D9: 2026-08-14 15:05 | E9: 托管系统
A10: 组合经理手工记录总资产 | B10: 1029000 | C10: 人民币元 | D10: 2026-08-14 15:10 | E10: 组合工作表
A11: 本周计划净流出 | B11: 50000 | C11: 人民币元 | D11: 2026-08-17 | E11: 客户已确认

Sheet 原始_持仓批次
A1: 原始数据 — 持仓批次明细
A3: 证券ID | B3: 证券类型 | C3: 行业或主题 | D3: 批次日期 | E3: 数量 | F3: 单位成本 | G3: 成本币种 | H3: 是否当日买入 | I3: 当前价格 | J3: 价格币种
A4: P01 | B4: A股 | C4: 电子 | D4: 2026-05-10 | E4: 2500 | F4: 43.2 | G4: 人民币 | H4: 否 | I4: 32.8 | J4: 人民币
A5: P01 | B5: A股 | C5: 电子 | D5: 2026-07-02 | E5: 1500 | F5: 37.5 | G5: 人民币 | H5: 否 | I5: 32.8 | J5: 人民币
A6: P01 | B6: A股 | C6: 电子 | D6: 2026-08-14 | E6: 1000 | F6: 31.9 | G6: 人民币 | H6: 是 | I6: 32.8 | J6: 人民币
A7: P02 | B7: A股 | C7: 计算机 | D7: 2026-03-18 | E7: 3000 | F7: 54.2 | G7: 人民币 | H7: 否 | I7: 58.4 | J7: 人民币
A8: P03 | B8: A股 | C8: 医药 | D8: 2026-04-11 | E8: 8000 | F8: 10.3 | G8: 人民币 | H8: 否 | I8: 9.62 | J8: 人民币
A9: P04 | B9: A股 | C9: 工业 | D9: 2026-01-20 | E9: 6000 | F9: 11.9 | G9: 人民币 | H9: 否 | I9: 12.35 | J9: 人民币
A10: P05 | B10: A股 | C10: 计算机 | D10: 2025-12-05 | E10: 2000 | F10: 82.4 | G10: 人民币 | H10: 否 | I10: 105 | J10: 人民币
A11: P06 | B11: 境内ETF | C11: 红利 | D11: 2026-02-06 | E11: 10000 | F11: 3.1 | G11: 人民币 | H11: 否 | I11: 2.88 | J11: 人民币
A12: P07 | B12: 港股ETF | C12: 海外科技 | D12: 2026-06-16 | E12: 10000 | F12: 16.4 | G12: 港币 | H12: 否 | I12: 15.3 | J12: 港币

Sheet 原始_行情与交易状态
A1: 原始数据 — 行情与可交易状态
A3: 证券ID | B3: 市场 | C3: 最新价格 | D3: 币种 | E3: 价格时间 | F3: 交易状态 | G3: 涨跌停状态 | H3: 当日买入数量 | I3: 可卖数量 | J3: 最小交易单位 | K3: 20日平均成交额_万元 | L3: 说明
A4: P01 | B4: 沪深 | C4: 32.8 | D4: 人民币 | E4: 2026-08-14 15:00 | F4: 正常 | G4: 无 | H4: 1000 | I4: 4000 | J4: 100 | K4: 8600 | L4: 当日买入部分按T+1管理
A5: P02 | B5: 沪深 | C5: 58.4 | D5: 人民币 | E5: 2026-08-14 15:00 | F5: 正常 | G5: 跌停 | H5: 0 | I5: 3000 | J5: 100 | K5: 2100 | L5: 收盘封单，次日成交不确定
A6: P03 | B6: 沪深 | C6: 9.62 | D6: 人民币 | E6: 2026-08-14 15:00 | F6: 正常 | G6: 无 | H6: 0 | I6: 8000 | J6: 100 | K6: 4700
A7: P04 | B7: 沪深 | C7: 12.35 | D7: 人民币 | E7: 2026-08-13 15:00 | F7: 停牌 | G7: 不适用 | H7: 0 | I7: 0 | J7: 100 | K7: 900 | L7: 8月14日全天停牌，复牌日未确定
A8: P05 | B8: 沪深 | C8: 105 | D8: 人民币 | E8: 2026-08-14 15:00 | F8: 正常 | G8: 无 | H8: 0 | I8: 2000 | J8: 100 | K8: 12800
A9: P06 | B9: 沪深 | C9: 2.88 | D9: 人民币 | E9: 2026-08-14 15:00 | F9: 正常 | G9: 无 | H9: 0 | I9: 10000 | J9: 100 | K9: 56000 | L9: 8月12日每份现金分配0.80元；8月11日未调整收盘价3.68元，调整后参考价2.88元
A10: P07 | B10: 香港 | C10: 15.3 | D10: 港币 | E10: 2026-08-14 16:00 | F10: 正常 | G10: 无 | H10: 0 | I10: 10000 | J10: 500 | K10: 12500 | L10: 港币兑人民币估值汇率0.92

Sheet 原始_风险暴露
A1: 原始数据 — 风险暴露
A3: 证券ID | B3: 风险分类 | C3: 组合分组 | D3: 近60日波动率 | E3: 内部风险等级 | F3: 与P05相关系数 | G3: 是否外币暴露
A4: P01 | B4: 成长 | C4: 科技 | D4: 0.38 | E4: 高 | F4: 0.72 | G4: 否
A5: P02 | B5: 成长 | C5: 科技 | D5: 0.44 | E5: 高 | F5: 0.81 | G5: 否
A6: P03 | B6: 防御 | C6: 医药 | D6: 0.25 | E6: 中 | F6: 0.18 | G6: 否
A7: P04 | B7: 周期 | C7: 工业 | D7: 0.29 | E7: 中 | F7: 0.22 | G7: 否
A8: P05 | B8: 成长 | C8: 科技 | D8: 0.46 | E8: 高 | F8: 1 | G8: 否
A9: P06 | B9: 防御 | C9: 红利 | D9: 0.17 | E9: 低 | F9: -0.05 | G9: 否
A10: P07 | B10: 成长 | C10: 科技 | D10: 0.31 | E10: 中高 | F10: 0.64 | G10: 是

Sheet 持仓勾稽与盈亏
A1: 持仓勾稽与浮动盈亏 (按证券汇总，成本按批次重建，总资产分母=1,032,660元)
A3: 证券ID | B3: 证券类型 | C3: 行业/主题 | D3: 风险等级 | E3: 总持仓数量 | F3: 总成本(元) | G3: 加权平均成本 | H3: 当前价格 | I3: 市值(元) | J3: 浮动盈亏(元) | K3: 盈亏率 | L3: 持仓权重 | M3: 可卖数量 | N3: 交易状态与备注
A4: P01 | B4: A股 | C4: 电子/科技 | D4: 高 | E4: =SUMIF(原始_持仓批次!A:A,"P01",原始_持仓批次!E:E) | F4: =SUMPRODUCT((原始_持仓批次!A$4:A$12="P01")*原始_持仓批次!E$4:E$12*原始_持仓批次!F$4:F$12) | G4: =F4/E4 | H4: 32.8 | I4: =E4*H4 | J4: =I4-F4 | K4: =IF(F4=0,"",J4/F4) | L4: =I4/1032660 | M4: 4000 | N4: 4000股今日可卖；1000股(8/14买入)T+1，8/17可卖
A5: P02 | B5: A股 | C5: 计算机/科技 | D5: 高 | E5: =SUMIF(原始_持仓批次!A:A,"P02",原始_持仓批次!E:E) | F5: =SUMPRODUCT((原始_持仓批次!A$4:A$12="P02")*原始_持仓批次!E$4:E$12*原始_持仓批次!F$4:F$12) | G5: =F5/E5 | H5: 58.4 | I5: =E5*H5 | J5: =I5-F5 | K5: =IF(F5=0,"",J5/F5) | L5: =I5/1032660 | M5: 3000 | N5: 8/14收盘跌停封单，次日成交不确定
A6: P03 | B6: A股 | C6: 医药/医药 | D6: 中 | E6: =SUMIF(原始_持仓批次!A:A,"P03",原始_持仓批次!E:E) | F6: =SUMPRODUCT((原始_持仓批次!A$4:A$12="P03")*原始_持仓批次!E$4:E$12*原始_持仓批次!F$4:F$12) | G6: =F6/E6 | H6: 9.62 | I6: =E6*H6 | J6: =I6-F6 | K6: =IF(F6=0,"",J6/F6) | L6: =I6/1032660 | M6: 8000 | N6: 正常交易
A7: P04 | B7: A股 | C7: 工业/工业 | D7: 中 | E7: =SUMIF(原始_持仓批次!A:A,"P04",原始_持仓批次!E:E) | F7: =SUMPRODUCT((原始_持仓批次!A$4:A$12="P04")*原始_持仓批次!E$4:E$12*原始_持仓批次!F$4:F$12) | G7: =F7/E7 | H7: 12.35 | I7: =E7*H7 | J7: =I7-F7 | K7: =IF(F7=0,"",J7/F7) | L7: =I7/1032660 | M7: 0 | N7: 8/14起停牌，复牌日未定；价格为8/13收盘价
A8: P05 | B8: A股 | C8: 计算机/科技 | D8: 高 | E8: =SUMIF(原始_持仓批次!A:A,"P05",原始_持仓批次!E:E) | F8: =SUMPRODUCT((原始_持仓批次!A$4:A$12="P05")*原始_持仓批次!E$4:E$12*原始_持仓批次!F$4:F$12) | G8: =F8/E8 | H8: 105 | I8: =E8*H8 | J8: =I8-F8 | K8: =IF(F8=0,"",J8/F8) | L8: =I8/1032660 | M8: 2000 | N8: 正常交易；组合经理提议暂不减持但未经审批
A9: P06 | B9: 境内ETF | C9: 红利/红利 | D9: 低 | E9: =SUMIF(原始_持仓批次!A:A,"P06",原始_持仓批次!E:E) | F9: =SUMPRODUCT((原始_持仓批次!A$4:A$12="P06")*原始_持仓批次!E$4:E$12*原始_持仓批次!F$4:F$12) | G9: =F9/E9 | H9: 2.88 | I9: =E9*H9 | J9: =I9-F9 | K9: =IF(F9=0,"",J9/F9) | L9: =I9/1032660 | M9: 10000 | N9: 8/12每份派现0.80元，已用除权参考价2.88元
A10: P07 | B10: 港股ETF | C10: 海外科技/科技 | D10: 中高 | E10: =SUMIF(原始_持仓批次!A:A,"P07",原始_持仓批次!E:E) | F10: =SUMPRODUCT((原始_持仓批次!A$4:A$12="P07")*原始_持仓批次!E$4:E$12*原始_持仓批次!F$4:F$12)*0.92 | G10: =F10/E10 | H10: 15.3 | I10: =E10*H10*0.92 | J10: =I10-F10 | K10: =IF(F10=0,"",J10/F10) | L10: =I10/1032660 | M10: 10000 | N10: 港币计价，估值汇率0.92；最小交易单位500份
A11: 合计 | E11: =SUM(E4:E10) | F11: =SUM(F4:F10) | I11: =SUM(I4:I10) | J11: =SUM(J4:J10) | L11: =SUM(L4:L10)
A12: 核验 | B12: 市值合计 vs 托管系统证券市值小计 | I12: =I11 | J12: 869820 | K12: =I12-J12 | N12: 差异应为0
A14: P06除权与总回报说明
A15: 原始成本(10000份×3.10) | B15: =10000*3.10
A16: 已收现金股息(10000份×0.80) | B16: =10000*0.80
A17: 当前市值(10000份×2.88) | B17: =10000*2.88
A18: 持仓浮动盈亏(不含股息) | B18: =28800-31000
A19: 总回报(含已收股息) | B19: =28800-31000+8000
A20: 说明 | B20: 可用现金分配造成的除权不视为投资损失；比较收益时使用调整后参考价2.88元，并加回已确认现金股息

Sheet 总资产双口径勾稽
A1: 总资产双口径勾稽 — 差异说明与采用口径
A3: 项目 | B3: 金额(元) | C3: 占比 | D3: 来源 | E3: 说明
A4: 证券市值小计 | B4: 869820 | C4: =B4/1032660 | D4: 托管系统 | E4: 7只持仓按截点价格计算，P07按0.92汇率折算
A5: 人民币可用现金 | B5: 142500 | C5: =B5/1032660 | D5: 资金系统 | E5: 含P06现金股息8000元(8/12到账)
A6: 美元现金折算 | B6: =3000*7.18 | C6: =B6/1032660 | D6: 资金系统+估值表 | E6: 3000美元×7.18汇率
A7: 待扣费用 | B7: -1200 | C7: =B7/1032660 | D7: 托管系统 | E7: 已发生未扣收费用
A8: 托管系统总资产(底账合计) | B8: =SUM(B4:B7) | C8: =B8/1032660 | D8: 托管系统 | E8: 可由以上四项完整复算，作为主口径
A10: 双口径对比
A11: 托管系统总资产 | B11: 1032660 | C11: 2026-08-14 15:05 | E11: 可由证券市值+现金+外币折算-待扣费用完整复算
A12: 组合经理手工记录总资产 | B12: 1029000 | C12: 2026-08-14 15:10 | E12: 记录时间晚5分钟，可能含手工调整项
A13: 差异(托管系统-手工记录) | B13: =B14-B15 | E13: 差额3,660元，占总资产0.35%
A15: 差异可能来源分析(无法从附件确定具体原因)
A16: 1. P04停牌估值差异：P04自8/14停牌，托管系统沿用8/13收盘价12.35元；组合经理可能对停牌证券计提了折价(若折价约0.61元/股，6000股对应约3,660元)。
A17: 2. 待扣费用处理差异：组合经理手工记录可能未扣除待扣费用1,200元，或对费用预提口径不同。
A18: 3. 记录时间差：托管系统15:05快照 vs 手工记录15:10，期间可能有资金系统变动。
A19: 4. 以上均为合理推断，附件未提供组合经理手工记录的计算明细，无法确认具体原因。
A21: 采用口径声明
A22: 本工作簿所有约束计算、权重、减仓数量均以托管系统底账口径 1,032,660 元为分母，因为该口径可由证券市值、现金、外币折算和待扣费用四项完整复算，证据链完整。
A23: 组合经理手工记录 1,029,000 元作为对照口径列示；若采用该口径，各项约束阈值同步收紧约0.35%，减仓数量需相应增加约1-2手，不改变约束超限/达标的方向性结论。
A24: 勾稽残差 3,660 元照实列出，未用其他资产或四舍五入抹平；建议组合经理提供手工记录的计算明细以查清差异来源。

Sheet 硬约束状态
A1: 硬约束状态表 — 未调整 vs 拟定方案 (分母: 托管系统口径)
A3: 约束名称 | B3: 阈值 | C3: 未调整值 | D3: 转出后(无减仓) | E3: 拟定方案后 | F3: 判定 | G3: 绑定/已消除 | H3: 达标所需动作 | I3: 对应规则号
A4: 单一证券市值上限(P05) | B4: ≤20% | C4: =210000/1032660 | D4: =210000/(1032660-50000) | E4: =189000/982392.23 | F4: 超限→达标 | G4: 已消除 | H4: 卖出P05至少200股(21,000元) | I4: R1
A5: 科技主题合计上限 | B5: ≤40% | C5: =689960/1032660 | D5: =689960/(1032660-50000) | E5: =390440/982392.23 | F5: 超限→达标 | G5: 最紧约束 | H5: 减持科技类约29.7万元(P07全清+P01 4200股+P05 200股) | I5: R1,R2,R3
A6: 高风险持仓合计上限 | B6: ≤45% | C6: =549200/1032660 | D6: =549200/(1032660-50000) | E6: =364200/982392.23 | F6: 超限→达标 | G6: 已消除 | H6: 减持高风险(P01+P05)约15.9万元 | I6: R1,R3
A7: 外币资产上限 | B7: ≤15% | C7: =162300/1032660 | D7: =162300/(1032660-50000) | E7: =21540/982392.23 | F7: 超限→达标 | G7: 已消除 | H7: 卖出P07全部10000份(港币资产) | I7: R2
A8: 转出后现金类资产下限 | B8: ≥10% | C8: =142500/1032660 | D8: =92500/(1032660-50000) | E8: =391752.23/982392.23 | F8: 超限→达标 | G8: 已消除 | H8: 减仓净回笼约29.9万元补充现金 | I8: R1,R2,R3
A10: 集中度分解(未调整，分母=1,032,660元)
A11: 主题分组 | B11: 包含标的 | C11: 市值(元) | D11: 权重 | E11: 阈值 | F11: 判定
A12: 科技 | B12: P01,P02,P05,P07 | C12: 689960 | D12: =C12/1032660 | E12: ≤40% | F12: 超限
A13: 医药 | B13: P03 | C13: 76960 | D13: =C13/1032660 | E13: — | F13: —
A14: 工业 | B14: P04 | C14: 74100 | D14: =C14/1032660 | E14: — | F14: —
A15: 红利 | B15: P06 | C15: 28800 | D15: =C15/1032660 | E15: — | F15: —
A16: 合计 | C16: =SUM(C12:C15) | D16: =SUM(D12:D15) | E16: — | F16: 应=100%
A18: 风险等级分解(未调整)
A19: 风险等级 | B19: 包含标的 | C19: 市值(元) | D19: 权重 | E19: 阈值 | F19: 判定
A20: 高 | B20: P01,P02,P05 | C20: 549200 | D20: =C20/1032660 | E20: ≤45% | F20: 超限
A21: 中高 | B21: P07 | C21: 140760 | D21: =C21/1032660 | E21: — | F21: —
A22: 中 | B22: P03,P04 | C22: 151060 | D22: =C22/1032660 | E22: — | F22: —
A23: 低 | B23: P06 | C23: 28800 | D23: =C23/1032660 | E23: — | F23: —
A24: 合计 | C24: =SUM(C20:C23) | D24: =C24/1032660 | E24: — | F24: 应=100%
A26: 外币暴露分解(未调整)
A27: 外币资产 | B27: 原币金额 | C27: 汇率 | D27: 折人民币(元) | E27: 权重
A28: P07港股ETF | B28: 153000港币 | C28: 0.92 | D28: =153000*0.92 | E28: =D28/1032660
A29: 美元现金 | B29: 3000美元 | C29: 7.18 | D29: =3000*7.18 | E29: =D29/1032660
A30: 外币合计 | D30: =SUM(D28:D29) | E30: =D30/1032660

Sheet 资金转出影响
A1: 资金转出影响分析 — 5万元转出对现金比例与风险约束的影响
A3: 项目 | B3: 转出前 | C3: 转出后(无减仓) | D3: 拟定减仓+转出后 | E3: 变化 | F3: 说明
A4: 总资产(元) | B4: 1032660 | C4: =1032660-50000 | D4: 982392.23 | E4: =D4-B4 | F4: 减仓扣费267.77元+转出50,000元
A5: 人民币现金(元) | B5: 142500 | C5: =142500-50000 | D5: 391752.23 | E5: =D5-B5 | F5: 减仓净回笼299,252.23元补充现金
A6: 现金占比 | B6: =142500/1032660 | C6: =92500/982660 | D6: =391752.23/982392.23 | E6: =D6-B6 | F6: 转出后无减仓仅9.41%，低于10%下限
A7: 证券市值(元) | B7: 869820 | C7: 869820 | D7: =869820-299520 | E7: =D7-B7 | F7: 减仓卖出P07+P05+P01合计299,520元
A8: 科技主题市值(元) | B8: 689960 | C8: 689960 | D8: 390440 | E8: =D8-B8 | F8: 减持科技299,520元
A9: 科技主题权重 | B9: =689960/1032660 | C9: =689960/982660 | D9: =390440/982392.23 | E9: =D9-B9 | F9: 转出使分母缩小，权重从66.81%升至70.21%
A10: 高风险市值(元) | B10: 549200 | C10: 549200 | D10: 364200 | E10: =D10-B10 | F10: 减持P01+P05合计158,760元
A11: 高风险权重 | B11: =549200/1032660 | C11: =549200/982660 | D11: =364200/982392.23 | E11: =D11-B11
A12: 外币资产(元) | B12: 162300 | C12: 162300 | D12: 21540 | E12: =D12-B12 | F12: P07全清后仅剩美元现金21,540元
A13: 外币权重 | B13: =162300/1032660 | C13: =162300/982660 | D13: =21540/982392.23 | E13: =D13-B13
A15: 优先处理持仓及理由
A16: P07(港股ETF) | B16: 第一优先 | C16: 外币超限+科技超限双重约束；全部卖出可同时解决外币约束并大幅削减科技敞口；流动性好(日均1.25亿元)，无T+1限制；500份整数交易，10000份可全部卖出。
A17: P01(A股电子) | B17: 第二优先 | C17: 科技+高风险双约束；4000股今日可卖，8/17全部5000股可卖；流动性好(日均8600万元)；卖出可同时降低科技和高风险敞口。按FIFO卖出批次1(2500股@43.20)、批次2(1500股@37.50)、批次3(200股@31.90)。
A18: P05(A股计算机) | B18: 第三优先(最低必要) | C18: 单票超限(20.34%)必须减持；仅卖出最低必要数量200股即可回到限内；组合经理'长期看好暂不减持'未经审批，不替代已批准上限。
A19: P02(A股计算机) | B19: 不可依赖 | C19: 8/14收盘跌停封单，次日能否成交不确定；不得写成已可成交；若8/17打开跌停可作为备选减仓标的，但主方案不依赖其成交。
A20: P04(A股工业) | B20: 不可交易 | C20: 8/14起停牌，复牌日未定，可卖数量为0；不得纳入减仓计划；复牌后需重新评估价格与流动性。
A21: P03/P06 | B21: 不需减持 | C21: P03(医药/防御)和P06(红利/低风险)不属于科技或高风险，减持它们不能解决核心约束；P06流动性极好但卖出仅补充现金，不降低科技敞口，当前现金已通过减仓科技满足。

Sheet 交易日历
A1: 交易日历 — 从as-of到最迟行动日
A3: 日历日 | B3: 星期 | C3: 是否交易日 | D3: 可执行时段说明 | E3: 资金可用/可划转 | F3: 备注(解冻/到账/截止)
A4: 2026-08-14 | B4: 周五 | C4: 是 | D4: 沪深9:30-11:30,13:00-15:00；港股9:30-12:00,13:00-16:00 | E4: 当日卖出资金T+1可用 | F4: 资料截点；P01买入1000股(T+1)；P02跌停；P04停牌；P06除权
A5: 2026-08-15 | B5: 周六 | C5: 否 | D5: 休市 | E5: 不可划转 | F5: 非交易日
A6: 2026-08-16 | B6: 周日 | C6: 否 | D6: 休市 | E6: 不可划转 | F6: 非交易日
A7: 2026-08-17 | B7: 周一 | C7: 是 | D7: 沪深9:30-11:30,13:00-15:00；港股9:30-12:00,13:00-16:00 | E7: 8/14卖出资金可用；当日卖出资金T+1可用 | F7: ★客户确认净转出5万元截止日；P01 T+1股份解冻可卖；减仓执行日；P02跌停状态待观察
A8: 2026-08-18 | B8: 周二 | C8: 是 | D8: 正常交易时段 | E8: 8/17卖出资金可用 | F8: 减仓后复核日；若8/17未成交可继续执行
A9: 2026-08-19 | B9: 周三 | C9: 是 | D9: 正常交易时段 | E9: 正常 | F9: 约束达标复核日
A10: 2026-08-20 | B10: 周四 | C10: 是 | D10: 正常交易时段 | E10: 正常 | F10: 监控日
A11: 2026-08-21 | B11: 周五 | C11: 是 | D11: 正常交易时段 | E11: 正常 | F11: 本周最后交易日；全面复核日
A13: 关键时点说明
A14: 1. as-of = 2026-08-14(周五)收盘后；所有'当前可执行'操作实际应在下一交易日(8/17周一)执行。
A15: 2. P01于8/14买入的1000股按T+1管理，8/17(周一)方可卖出；8/17时P01全部5000股可卖。
A16: 3. 8/17为客户确认的5万元转出截止日，必须在当日交易时段内完成减仓并确保资金可划转。
A17: 4. A股卖出资金T+1交收：8/17卖出的资金8/18方可转出；因此5万元转出应优先使用账上已有现金142,500元，减仓回笼资金用于补充现金比例。
A18: 5. P02若8/17继续跌停，无法成交；主方案不依赖P02卖出。
A19: 6. P04停牌期间可卖数量为0，复牌日未确定，不得纳入减仓计划。

Sheet 调仓方案与交易明细
A1: 调仓方案与交易明细 — 拟定减仓方案(执行日: 2026-08-17 周一)
A3: 证券ID | B3: 证券名称/类型 | C3: 卖出数量 | D3: 委托价格 | E3: 价格币种 | F3: 成交金额(元) | G3: 佣金(元) | H3: 印花税(元) | I3: 其他费用(元) | J3: 费用合计(元) | K3: 净回笼(元) | L3: 卖出成本(元) | M3: 实现盈亏(元) | N3: 卖出批次/备注
A4: P07 | B4: 港股ETF/海外科技 | C4: 10000 | D4: 15.3 | E4: 港币 | F4: =10000*15.30*0.92 | G4: 0 | H4: 0 | I4: =F4*0.001 | J4: =G4+H4+I4 | K4: =F4-J4 | L4: =10000*16.40*0.92 | M4: =F4-L4-J4 | N4: 全部卖出；500份整数×20手；综合费率0.10%
A5: P05 | B5: A股/计算机 | C5: 200 | D5: 105 | E5: 人民币 | F5: =200*105 | G5: =MAX(F5*0.0003,5) | H5: =F5*0.0005 | I5: 0 | J5: =G5+H5+I5 | K5: =F5-J5 | L5: =200*82.40 | M5: =F5-L5-J5 | N5: 最低必要减持(单票超限)；100股整数×2手；FIFO
A6: P01 | B6: A股/电子 | C6: 4200 | D6: 32.8 | E6: 人民币 | F6: =4200*32.80 | G6: =MAX(F6*0.0003,5) | H6: =F6*0.0005 | I6: 0 | J6: =G6+H6+I6 | K6: =F6-J6 | L6: =2500*43.20+1500*37.50+200*31.90 | M6: =F6-L6-J6 | N6: FIFO:批次1(2500@43.20)+批次2(1500@37.50)+批次3(200@31.90)；100股整数×42手
A7: 合计 | C7: =SUM(C4:C6) | F7: =SUM(F4:F6) | G7: =SUM(G4:G6) | H7: =SUM(H4:H6) | I7: =SUM(I4:I6) | J7: =SUM(J4:J6) | K7: =SUM(K4:K6) | L7: =SUM(L4:L6) | M7: =SUM(M4:M6)
A9: 费用勾稽核验
A10: P07隐含费率 | B10: =J4/F4 | C10: 题设0.10% | D10: =IF(ABS(B10-0.001)<0.0001,"一致","差异")
A11: P05隐含费率 | B11: =J5/F5 | C11: 佣金0.03%(最低5元)+印花税0.05% | D11: =IF(ABS(B11-(6.3+10.5)/21000)<0.0001,"一致","差异")
A12: P01隐含费率 | B12: =J6/F6 | C12: 佣金0.03%+印花税0.05% | D12: =IF(ABS(B12-0.0008)<0.0001,"一致","差异")
A14: 调整后组合状态(减仓+5万元转出后)
A15: 项目 | B15: 金额(元) | C15: 说明
A16: 减仓成交总额 | B16: =F7 | C16: P07+P05+P01卖出毛额
A17: 减仓费用合计 | B17: =J7 | C17: 佣金+印花税+港股综合费
A18: 减仓净回笼 | B18: =K7 | C18: 成交总额-费用
A19: 减仓实现盈亏(扣费后) | B19: =M7 | C19: 负数为净亏损
A20: 转出资金 | B20: 50000 | C20: 客户确认8/17净转出
A21: 调整后总资产 | B21: =1032660-B20-B17 | C21: 原总资产-转出-费用
A22: 调整后人民币现金 | B22: =142500+B18-B20 | C22: 原现金+净回笼-转出
A23: 调整后现金占比 | B23: =B22/B21 | C23: 人民币现金/总资产
A24: 调整后证券市值 | B24: =869820-B16 | C24: 原市值-减仓成交
A26: 调整后持仓明细
A27: 证券ID | B27: 剩余数量 | C27: 当前价格 | D27: 市值(元) | E27: 权重 | F27: 主题 | G27: 风险等级
A28: P01 | B28: 800 | C28: 32.8 | D28: =B28*C28 | E28: =D28/B21 | F28: 电子/科技 | G28: 高
A29: P02 | B29: 3000 | C29: 58.4 | D29: =B29*C29 | E29: =D29/B21 | F29: 计算机/科技 | G29: 高
A30: P03 | B30: 8000 | C30: 9.62 | D30: =B30*C30 | E30: =D30/B21 | F30: 医药/医药 | G30: 中
A31: P04 | B31: 6000 | C31: 12.35 | D31: =B31*C31 | E31: =D31/B21 | F31: 工业/工业 | G31: 中
A32: P05 | B32: 1800 | C32: 105 | D32: =B32*C32 | E32: =D32/B21 | F32: 计算机/科技 | G32: 高
A33: P06 | B33: 10000 | C33: 2.88 | D33: =B33*C33 | E33: =D33/B21 | F33: 红利/红利 | G33: 低
A34: P07 | B34: 0 | C34: 15.3 | D34: 0 | E34: =D34/B21 | F34: 海外科技/科技 | G34: 中高
A35: 合计 | D35: =SUM(D28:D34) | E35: =SUM(E28:E34)

Sheet 条件规则
A1: if→then 条件交易规则 — 区分正常成交/无法成交/风险继续扩大
A3: 规则号 | B3: 触发条件(可观察阈值+截止时点) | C3: 方向自检 | D3: 动作 | E3: 数量及口径(基准持仓) | F3: 目标权重 | G3: 预计费用与净回笼 | H3: 执行时点 | I3: 未成交时的后手 | J3: 交易后复核项
A4: R1 | B4: If 8/17(周一)9:30开盘后P07报价≥15.00港币且买盘存在 → Then 限价卖出P07 | C4: P07下跌会压低其权重与外币敞口(改善约束)，因此触发条件用'报价≥阈值'而非下跌；卖出动作本身降低科技和外币敞口 | D4: 以限价15.30港币挂单卖出P07全部10000份(500份整数×20手)；若开盘价低于15.00则下调限价至买一价但不低于14.50 | E4: 累计总卖出量10000份，基准持仓=10000份(全部清仓) | F4: P07权重降至0%；外币权重降至约2.19% | G4: 成交约140,760元；费用约140.76元(0.10%)；净回笼约140,619.24元 | H4: 8/17 9:30-16:00(港股交易时段) | I4: 若全日无法成交(停牌/无买盘)：外币约束仍超限，标记'待成交后复核'；8/18继续挂单；若连续3日无法成交，启动备选方案(卖出P01追加1000股补充现金，但外币约束需待P07成交) | J4: 成交后核对：P07持仓=0；港币现金到账；外币权重≤15%；科技权重下降
A5: R2 | B5: If 8/17(周一)9:30开盘后P05报价≥102元且可卖数量≥200 → Then 限价卖出P05 | C5: P05上涨会恶化单票超限(权重上升)，因此触发条件为'报价≥阈值'；卖出降低单票和科技敞口 | D5: 以限价105元挂单卖出P05共200股(100股整数×2手)；此为单票超限的最低必要减持数量 | E5: 累计总卖出量200股，基准持仓=2000股；卖出后剩余1800股 | F5: P05单票权重降至约19.24% | G5: 成交约21,000元；佣金6.30元+印花税10.50元=16.80元；净回笼约20,983.20元 | H5: 8/17 9:30-15:00(沪深交易时段) | I5: 若涨停无法卖出：单票约束仍超限，标记'待成交后复核'；8/18继续挂单；若连续2日无法成交，考虑卖出P01追加500股以间接降低P05权重占比(但P05单票绝对值仍超限，须最终卖出P05) | J5: 成交后核对：P05持仓=1800股；P05权重≤20%；实现盈亏约+4,503元
A6: R3 | B6: If 8/17(周一)9:30开盘后P01报价≥32.00元且可卖数量≥4200 → Then 限价卖出P01 | C6: P01上涨会恶化科技和高风险超限；卖出降低两者敞口。8/17时T+1股份已解冻，全部5000股可卖 | D6: 以限价32.80元挂单卖出P01共4200股(100股整数×42手)；FIFO批次：批次1(2500@43.20)+批次2(1500@37.50)+批次3(200@31.90) | E6: 累计总卖出量4200股，基准持仓=5000股；卖出后剩余800股(批次3剩余) | F6: P01权重降至约2.67%；科技+高风险敞口大幅下降 | G6: 成交约137,760元；佣金41.33元+印花税68.88元=110.21元；净回笼约137,649.79元 | H6: 8/17 9:30-15:00(沪深交易时段) | I6: 若部分成交(如仅成交3000股)：已成交部分计入，未成交1200股8/18继续挂单；若全日无法成交，科技约束仍超限，8/18优先卖出P01；若P01连续2日无法成交，启动备选(卖出P03 5000股补充现金，但不解决科技约束，须最终卖出科技标的) | J6: 成交后核对：P01持仓=800股；科技权重≤40%；高风险权重≤45%；实现盈亏约-32,980元
A7: R4 | B7: If 8/17 P02打开跌停(成交价>58.40的跌停价)且买盘充足 → Then 可选择性卖出P02 | C7: P02上涨恶化科技和高风险超限；但P02为浮盈仓位，卖出可实现正收益。此为备选规则，主方案不依赖P02成交 | D7: 若R1-R3全部成交后科技仍超限( unlikely )，以限价卖出P02不超过1000股；否则不主动卖出P02 | E7: 本阶段追加量0-1000股，基准持仓=3000股；仅在R1-R3成交后科技仍超限时启用 | F7: 每卖出1000股降低科技权重约1.02个百分点 | G7: 每1000股成交约58,400元；费用约46.72元；净回笼约58,353.28元 | H7: 8/17-8/18 沪深交易时段(仅在打开跌停后) | I7: 若继续跌停：不执行，标记'无法评估成交'；主方案已通过R1-R3满足约束，无需依赖P02 | J7: 若执行：核对P02持仓减少；科技权重复核；实现盈亏为正
A8: R5 | B8: If 减仓完成后科技类标的持续上涨导致科技权重再次突破40%(以方案后最高价计算) → Then 追加减仓 | C8: 科技标的上涨使权重恶化(方向正确)；触发基准使用方案开始后的历史最高完整收盘价，只上移不下调 | D8: 若科技权重>40%，按P02(若可卖)→P01剩余→P05剩余的顺序追加卖出，每次卖出100股(P02/P01)或100股(P05)，直至科技权重≤39%(留1个百分点缓冲) | E8: 本阶段追加量，每次100股，基准持仓=方案后持仓；累计追加量不超过剩余可卖数量 | F8: 科技权重回落至≤39% | G8: 每100股P02约5,840元/费用约4.67元；每100股P01约328元/费用约5元(最低佣金)；每100股P05约10,500元/费用约5.25元 | H8: 触发后下一交易日9:30 | I8: 若追加卖出标的停牌/跌停：跳过该标的，按下一顺序卖出；若全部科技标的不可交易，标记'约束持续超限，待复牌后处理'，期间禁止加仓任何科技标的 | J8: 每次追加后复核科技权重、单票权重、高风险权重；移动基准更新为新的最高价
A9: R6 | B9: If 8/17 15:00前5万元转出资金未备妥(人民币可取资金<50,000) → Then 优先变现 | C9: 转出截止日资金不足是直接违约风险；现金类资产不足时必须优先变现最具流动性的标的 | D9: 优先卖出P06(境内ETF，日均5.6亿元，流动性最好)不超过5000份补充现金；若P06卖出仍不足，卖出P03不超过2000股 | E9: 本阶段追加量，P06最多5000份(基准10000份)；P03最多2000股(基准8000股) | F9: 确保人民币可取资金≥50,000元+转账在途 | G9: P06每1000份成交约2,880元/费用约5元(最低佣金)；P03每1000股成交约9,620元/费用约7.70元 | H9: 8/17 9:30-14:30(确保资金在转账截止前到账) | I9: 若P06/P03均无法成交：立即通知客户转出可能延迟；使用美元现金结汇(若允许)作为最后手段；不得卖出停牌P04或跌停P02 | J9: 转出完成后核对：人民币现金余额；现金占比≥10%；若卖出了P06/P03，重新核对所有约束
A10: R7 | B10: If P04复牌且复牌首日开盘价较停牌前(12.35元)下跌超过10% → Then 评估是否止损 | C10: P04复牌下跌会造成实际损失；但P04不属于科技/高风险，下跌不恶化核心约束。触发条件为'下跌超10%'(恶化绝对损失额) | D10: 若复牌下跌>10%且组合整体波动率上升，卖出P04不超过3000股止损；若下跌≤10%或市场企稳，暂不卖出，继续监控 | E10: 本阶段追加量0-3000股，基准持仓=6000股；仅在复牌后评估 | F10: 控制单只停牌股复牌风险 | G10: 每1000股成交约11,115元(按-10%计)/费用约8.89元 | H10: P04复牌后首个交易日(日期待定) | I10: 若复牌即跌停无法卖出：标记'无法成交，待打开跌停后处理'；设置移动止损线(复牌最高价-8%) | J10: 复牌后重新计算P04市值和总资产；核对所有约束权重(分母变化)
A12: 规则执行总原则
A13: 1. 所有卖出均以限价挂单方式执行，是否成交取决于当时买盘与涨跌停状态；未成交则转入对应后手规则，不得写成'已成交'。
A14: 2. 执行顺序：R1(P07)→R2(P05)→R3(P01)，因为P07同时解决外币和科技约束，优先级最高；R2为单票超限的最低必要操作；R3为科技和高风险约束的主要减量。
A15: 3. 任何标的在停牌、跌停或涨跌停状态下，依赖该报价的交易后权重和风险标'无法评估'，不得用陈旧价填造；未成交仓位不得写入'已合规'。
A16: 4. 硬约束仍超限期间，禁止加仓、回补或做T等扩大该敞口的动作；等复核显示约束回到限内后再评估。
A17: 5. 本规则集仅用于调仓前分析，不代表任何交易已经下达或执行；实际执行前须由组合经理确认报价、可卖量和账户状态。

Sheet 情景与压力
A1: 情景与压力测试 — 调整前 vs 拟定方案后 (逐日复合)
A3: 情景名 | B3: 冲击路径定义 | C3: 调整前损失额(元) | D3: 调整前损失率 | E3: 方案后损失额(元) | F3: 方案后损失率 | G3: 是否最不利 | H3: 与阈值比较/说明
A4: 温和冲击 (1日) | B4: 科技类标的单日下跌5%；其余标的持平；外币汇率不变 | C4: =(164000+175200+210000+140760)*0.05 | D4: =C4/1032660 | E4: =(26240+175200+189000+0)*0.05 | F4: =E4/982392.23 | G4: 否 | H4: 方案后损失额下降约64%；科技敞口大幅缩减
A5: 中度冲击 (2日复合) | B5: Day1:科技类跌8%，高风险类跌5%，外币资产跌3%(汇率)；Day2:科技类在Day1收盘价基础上再跌5%，其余持平；逐日复合 | C5: =((164000+175200+210000+140760)*(1-0.08)*(1-0.05)-(164000+175200+210000+140760))+(140760+21540)*0.03 | D5: =C5/1032660 | E5: =((26240+175200+189000+0)*(1-0.08)*(1-0.05)-(26240+175200+189000+0))+(0+21540)*0.03 | F5: =E5/982392.23 | G5: 否 | H5: 两日复合下跌约12.6%(科技)；方案后损失率显著降低
A6: 严重冲击 (3日复合) | B6: Day1:科技类跌10%，高风险类跌8%，外币跌5%，防御类跌3%；Day2:科技类再跌7%，高风险再跌5%；Day3:科技类再跌5%；逐日复合，非科技类Day2-3持平 | C6: =((164000+175200+210000+140760)*(1-0.10)*(1-0.07)*(1-0.05)-(164000+175200+210000+140760))+((76960+28800)*0.03)+((140760+21540)*0.05) | D6: =C6/1032660 | E6: =((26240+175200+189000+0)*(1-0.10)*(1-0.07)*(1-0.05)-(26240+175200+189000+0))+((76960+28800)*0.03)+((0+21540)*0.05) | F6: =E6/982392.23 | G6: 是★ | H6: 最不利情景；科技三日累计跌约20%；方案后损失率约为调整前的40%
A7: P02连续跌停 (3日) | B7: P02连续3日跌停(每日-10%)，其余标的持平；模拟P02负面持续发酵且无法卖出 | C7: =175200*(1-(0.9)^3) | D7: =C7/1032660 | E7: =175200*(1-(0.9)^3) | F7: =E7/982392.23 | G7: 否 | H7: P02在两个方案中均未卖出(主方案不依赖P02)；损失额相同但方案后分母更小，损失率略高
A8: P04复牌补跌 (1日) | B8: P04复牌首日下跌15%(停牌补跌)，其余标的持平；P04不属于科技/高风险 | C8: =74100*0.15 | D8: =C8/1032660 | E8: =74100*0.15 | F8: =E8/982392.23 | G8: 否 | H8: P04在两个方案中均保留；绝对损失相同；复牌后需按R7规则评估
A10: 压力测试结论
A11: 1. 最不利情景为'严重冲击(3日复合)'：科技类三日累计下跌约20%(1-0.9×0.93×0.95≈20.4%)，调整前组合损失率约13.7%，方案后约5.5%。
A12: 2. 拟定方案在所有压力情景下均显著降低损失额和损失率，核心原因是科技敞口从689,960元降至390,440元(降幅43.4%)。
A13: 3. P02连续跌停情景下，由于主方案未卖出P02，绝对损失额在两个方案中相同；但方案后总资产更小，损失率略高。若P02风险持续，应在打开跌停后按R4规则评估减持。
A14: 4. P04复牌补跌不影响核心约束(工业/中风险)，但复牌后总资产分母变化，需重新核对所有约束权重。
A15: 5. 以上情景为基于附件波动率和相关性的假设性冲击，不代表预测；实际损失取决于市场走势和成交价格。

Sheet 假设与缺失
A1: 假设与缺失清单 — 证据边界与待补事项
A3: 序号 | B3: 条目 | C3: 类型 | D3: 来源或推断依据 | E3: 影响哪些结论/补齐后需重算什么
A4: 1 | B4: 总资产采用托管系统底账口径1,032,660元 | C4: 已确认事实 | D4: 可由证券市值869,820+人民币现金142,500+美元折算21,540-待扣费用1,200完整复算 | E4: 所有约束权重和减仓数量的分母；若改用组合经理口径1,029,000元，阈值同步收紧约0.35%
A5: 2 | B5: 组合经理手工记录与托管系统差异3,660元 | C5: 仍缺证据 | D5: 附件未提供手工记录的计算明细；可能为P04停牌折价、待扣费用处理或记录时间差 | E5: 差异不改变约束超限/达标的方向性结论；建议组合经理提供明细以查清残差
A6: 3 | B6: P04停牌期间市值沿用8/13收盘价12.35元 | C6: 合理推断 | D6: 附件说明P04自8/14停牌、复牌日未定，无其他估值来源 | E6: P04市值和总资产；复牌后需按实际价格重算所有约束权重
A7: 4 | B7: P06现金股息8,000元已到账并计入人民币现金 | C7: 合理推断 | D7: 附件说明8/12每份派现0.80元，资金系统现金余额142,500元应含此股息 | E7: 现金金额和现金占比；若股息未到账，现金需扣减8,000元，现金占比下降约0.8个百分点
A8: 5 | B8: 减仓执行价格采用8/14收盘价 | C8: 合理推断 | D8: 附件提供的最新价格为8/14收盘价；实际执行价格取决于8/17市场报价 | E8: 成交金额、费用、净回笼和实现盈亏；实际价格波动±5%时，科技权重偏差约±1个百分点，需按R5规则动态调整
A9: 6 | B9: P02在8/17能否打开跌停未知 | C9: 仍缺证据 | D9: 附件说明8/14收盘跌停封单，次日成交不确定 | E9: 主方案不依赖P02成交；若8/17打开跌停，可按R4选择性卖出；若继续跌停，不影响方案可行性
A10: 7 | B10: 卖出批次采用FIFO(先进先出) | C10: 合理推断 | D10: 附件未指定卖出批次匹配方法；FIFO为通行默认 | E10: P01实现盈亏金额；若采用LIFO或指定批次，P01实现盈亏差异约±3,000元
A11: 8 | B11: 港股ETF综合费用按成交额0.10%估算 | C11: 已确认事实 | D11: 附件《账户授权与组合约束说明》第三条明确 | E11: P07卖出费用和净回笼；实际费用可能含平台费等，以券商结算为准
A12: 9 | B12: 美元现金不纳入'人民币及可随时变现的现金类资产' | C12: 合理推断 | D12: 约束原文为'人民币及可随时变现的现金类资产'，美元现金非人民币；附件未明确是否将美元结汇后计入 | E12: 现金占比约束；若美元结汇后可计入，现金占比上升约2.2个百分点，约束更易达标
A13: 10 | B13: 压力情景冲击幅度为假设性设定 | C13: 合理推断 | D13: 基于附件提供的近60日波动率(P01=0.38,P02=0.44,P05=0.46)和相关系数设定；非题面定义 | E13: 压力测试损失额和损失率；若题面给定具体冲击路径，需按题面逐日复合重算
A14: 11 | B14: P05'长期看好暂不减持'为组合经理个人意见 | C14: 已确认事实 | D14: 附件第五条明确：未经客户确认，未形成风险例外审批，不能替代已批准上限 | E14: P05减持数量；若后续取得正式风险例外审批，可调整P05减持量并相应增加P01/P07减持
A15: 12 | B15: 账户不得融资融券或使用场外杠杆 | C15: 已确认事实 | D15: 附件第一条明确 | E15: 所有方案均不涉及杠杆；若后续允许杠杆，约束计算方式需调整
... A17: 14 | B17: P07港币卖出后资金是否即时可换汇未明确 | C17: 仍缺证据 | D17: 附件未说明港股卖出资金的交收和换汇安排 | E17: 外币约束和现金约束；若港币卖出后需T+2才可换汇，外币敞口在交收日前仍存在
A19: 非执行声明
A20: 本工作簿仅用于调仓前分析与交易纪律设计，不代表任何交易已经下达或执行。
A21: 所有价格、数量和费用均基于附件提供的截点数据估算，实际执行以券商系统成交回报为准。
A22: 本分析不保证回本或保证收益，不构成投资建议；过往表现不代表未来收益。
A23: 执行任何交易前，须由组合经理确认最新报价、可卖数量、账户资金状态和市场涨跌停情况。
