Workbook

Sheet 决策摘要
A1: 组合持仓诊断与交易纪律 — 决策摘要（截点 2026-08-14 收盘，北京时间）
A3: 项 | B3: 值
A4: 结论 | B4: 周一(8/17)在仅用可正常成交标的前提下，卖P01 4000股+P07 10000份+P05 300股，即可把科技/高风险/单票/外币全部压回限额，并备妥5万元转出；P02跌停、P04停牌当日不可卖。
A5: 最紧约束 | B5: 科技主题：当前66.81%，限额40%，须压降科技市值约29.7万元(提款后口径)。
A6: 首要动作 | B6: 8/17限价卖P01 4000股、P07 10000份、P05 300股；P02若开板可替代部分卖出。
A7: 最迟行动日 | B7: 2026-08-17(周一)主路径；P01当日买入1000股8/18(周二)解禁为后手。
A8: 未决事项 | B8: ①手工总资产1,029,000与托管1,032,660差3,660无法分解；②P04复牌日未定；③P07结算币种需券商确认。
A10: 指标 | B10: 当前值(8/14) | C10: 限额 | D10: 主路径交易+提款后 | E10: 判定
A11: 科技主题占比 | B11: =硬约束状态!C5 -> 0.66813859 | C11: ≤40% | D11: =硬约束状态!E5 -> 0.39342864 | E11: =硬约束状态!F5 -> 超限→达标
A12: 高风险持仓占比 | B12: =硬约束状态!C6 -> 0.53183042 | C12: ≤45% | D12: =硬约束状态!E6 -> 0.39342864 | E12: =硬约束状态!F6 -> 超限→达标
A13: 最大单票(P05) | B13: =硬约束状态!C4 -> 0.20335832 | C13: ≤20% | D13: =硬约束状态!E4 -> 0.1816999 | E13: =硬约束状态!F4 -> 超限→达标
A14: 外币资产占比 | B14: =硬约束状态!C7 -> 0.15716693 | C14: ≤15% | D14: =硬约束状态!E7 -> 0.021926139 | E14: =硬约束状态!F7 -> 超限→达标
A15: 现金类占比 | B15: =硬约束状态!C8 -> 0.11605235 | C15: ≥10% | D15: =硬约束状态!E8 -> 0.42470859 | E15: =硬约束状态!F8 -> 达标
A17: 本工作簿仅用于调仓前分析，不代表已下单；不保证回本或收益；价格为8/14收盘，周一按实际报价重算数量。

Sheet 输入_账户
A1: 字段 | B1: 数值 | C1: 币种或单位 | D1: 记录时间 | E1: 来源
A2: 证券市值小计 | B2: 869820 | C2: 人民币元 | D2: 2026-08-14 15:05 | E2: 托管系统
A3: 人民币可用现金 | B3: 142500 | C3: 人民币元 | D3: 2026-08-14 15:05 | E3: 资金系统
A4: 美元现金 | B4: 3000 | C4: 美元 | D4: 2026-08-14 15:05 | E4: 资金系统
A5: 美元兑人民币折算汇率 | B5: 7.18 | C5: 人民币/美元 | D5: 2026-08-14 15:00 | E5: 内部估值表
A6: 待扣费用 | B6: 1200 | C6: 人民币元 | D6: 2026-08-14 15:05 | E6: 托管系统
A7: 账户总资产记录 | B7: 1032660 | C7: 人民币元 | D7: 2026-08-14 15:05 | E7: 托管系统
A8: 组合经理手工记录总资产 | B8: 1029000 | C8: 人民币元 | D8: 2026-08-14 15:10 | E8: 组合工作表
A9: 本周计划净流出 | B9: 50000 | C9: 人民币元 | D9: 2026-08-17 | E9: 客户已确认

Sheet 输入_持仓批次
A1: 证券ID | B1: 证券类型 | C1: 行业或主题 | D1: 批次日期 | E1: 数量 | F1: 单位成本 | G1: 成本币种 | H1: 是否当日买入 | I1: 当前价格 | J1: 价格币种
A2: P01 | B2: A股 | C2: 电子 | D2: 2026-05-10 | E2: 2500 | F2: 43.2 | G2: 人民币 | H2: 否 | I2: 32.8 | J2: 人民币
A3: P01 | B3: A股 | C3: 电子 | D3: 2026-07-02 | E3: 1500 | F3: 37.5 | G3: 人民币 | H3: 否 | I3: 32.8 | J3: 人民币
A4: P01 | B4: A股 | C4: 电子 | D4: 2026-08-14 | E4: 1000 | F4: 31.9 | G4: 人民币 | H4: 是 | I4: 32.8 | J4: 人民币
A5: P02 | B5: A股 | C5: 计算机 | D5: 2026-03-18 | E5: 3000 | F5: 54.2 | G5: 人民币 | H5: 否 | I5: 58.4 | J5: 人民币
A6: P03 | B6: A股 | C6: 医药 | D6: 2026-04-11 | E6: 8000 | F6: 10.3 | G6: 人民币 | H6: 否 | I6: 9.62 | J6: 人民币
A7: P04 | B7: A股 | C7: 工业 | D7: 2026-01-20 | E7: 6000 | F7: 11.9 | G7: 人民币 | H7: 否 | I7: 12.35 | J7: 人民币
A8: P05 | B8: A股 | C8: 计算机 | D8: 2025-12-05 | E8: 2000 | F8: 82.4 | G8: 人民币 | H8: 否 | I8: 105 | J8: 人民币
A9: P06 | B9: 境内ETF | C9: 红利 | D9: 2026-02-06 | E9: 10000 | F9: 3.1 | G9: 人民币 | H9: 否 | I9: 2.88 | J9: 人民币
A10: P07 | B10: 港股ETF | C10: 海外科技 | D10: 2026-06-16 | E10: 10000 | F10: 16.4 | G10: 港币 | H10: 否 | I10: 15.3 | J10: 港币

Sheet 输入_行情状态
A1: 证券ID | B1: 市场 | C1: 最新价格 | D1: 币种 | E1: 价格时间 | F1: 交易状态 | G1: 涨跌停状态 | H1: 当日买入数量 | I1: 可卖数量 | J1: 最小交易单位 | K1: 20日平均成交额_万元 | L1: 说明
A2: P01 | B2: 沪深 | C2: 32.8 | D2: 人民币 | E2: 2026-08-14 15:00 | F2: 正常 | G2: 无 | H2: 1000 | I2: 4000 | J2: 100 | K2: 8600 | L2: 当日买入部分按T+1管理
A3: P02 | B3: 沪深 | C3: 58.4 | D3: 人民币 | E3: 2026-08-14 15:00 | F3: 正常 | G3: 跌停 | H3: 0 | I3: 3000 | J3: 100 | K3: 2100 | L3: 收盘封单，次日成交不确定
A4: P03 | B4: 沪深 | C4: 9.62 | D4: 人民币 | E4: 2026-08-14 15:00 | F4: 正常 | G4: 无 | H4: 0 | I4: 8000 | J4: 100 | K4: 4700
A5: P04 | B5: 沪深 | C5: 12.35 | D5: 人民币 | E5: 2026-08-13 15:00 | F5: 停牌 | G5: 不适用 | H5: 0 | I5: 0 | J5: 100 | K5: 900 | L5: 8月14日全天停牌，复牌日未确定
A6: P05 | B6: 沪深 | C6: 105 | D6: 人民币 | E6: 2026-08-14 15:00 | F6: 正常 | G6: 无 | H6: 0 | I6: 2000 | J6: 100 | K6: 12800
A7: P06 | B7: 沪深 | C7: 2.88 | D7: 人民币 | E7: 2026-08-14 15:00 | F7: 正常 | G7: 无 | H7: 0 | I7: 10000 | J7: 100 | K7: 56000 | L7: 8月12日每份现金分配0.80元；8月11日未调整收盘3.68，调整后参考价2.88
A8: P07 | B8: 香港 | C8: 15.3 | D8: 港币 | E8: 2026-08-14 16:00 | F8: 正常 | G8: 无 | H8: 0 | I8: 10000 | J8: 500 | K8: 12500 | L8: 港币兑人民币估值汇率0.92

Sheet 输入_风险暴露
A1: 证券ID | B1: 风险分类 | C1: 组合分组 | D1: 近60日波动率 | E1: 内部风险等级 | F1: 与P05相关系数 | G1: 是否外币暴露
A2: P01 | B2: 成长 | C2: 科技 | D2: 0.38 | E2: 高 | F2: 0.72 | G2: 否
A3: P02 | B3: 成长 | C3: 科技 | D3: 0.44 | E3: 高 | F3: 0.81 | G3: 否
A4: P03 | B4: 防御 | C4: 医药 | D4: 0.25 | E4: 中 | F4: 0.18 | G4: 否
A5: P04 | B5: 周期 | C5: 工业 | D5: 0.29 | E5: 中 | F5: 0.22 | G5: 否
A6: P05 | B6: 成长 | C6: 科技 | D6: 0.46 | E6: 高 | F6: 1 | G6: 否
A7: P06 | B7: 防御 | C7: 红利 | D7: 0.17 | E7: 低 | F7: -0.05 | G7: 否
A8: P07 | B8: 成长 | C8: 科技 | D8: 0.31 | E8: 中高 | F8: 0.64 | G8: 是

Sheet 勾稽与盈亏
A1: 账户勾稽、批次成本与浮动盈亏（口径：人民币元；P07按0.92折算）
A3: 一、两套总资产勾稽
A4: 项目 | B4: 公式/口径 | C4: 金额(元)
A5: 证券市值小计 | B5: 托管系统 | C5: =输入_账户!B2 -> 869820
A6: 人民币可用现金 | B6: 资金系统 | C6: =输入_账户!B3 -> 142500
A7: 美元现金折人民币 | B7: 3000×7.18 | C7: =输入_账户!B4*输入_账户!B5 -> 21540
A8: 减：待扣费用 | B8: 托管系统 | C8: =-输入_账户!B6 -> -1200
A9: 托管锚总资产(净) | B9: 市值+人民币现金+美元折汇-待扣 | C9: =C5+C6+C7+C8 -> 1032660
A10: 托管系统账面记录 | B10: 托管系统 | C10: =输入_账户!B7 -> 1032660
A11: 勾稽残差(计算值-账面记录) | B11: 应=0 | C11: =C9-C10 -> 0
A12: 组合经理手工锚总资产 | B12: 组合工作表 | C12: =输入_账户!B8 -> 1029000
A13: 两锚差额(托管-手工) | B13: 无法从附件分解 | C13: =C9-C12 -> 3660
A14: 采用口径：以可逐项勾稽的托管锚(净, C9)为分母；手工锚差额3,660元列入假设与缺失清单，不抹平。
A16: 二、逐标的成本、市值与浮动盈亏
A17: 证券ID | B17: 行业/主题 | C17: 总数量 | D17: 原币现价 | E17: 折算RMB单价 | F17: 市值RMB | G17: 总成本RMB | H17: 浮动盈亏RMB | I17: 成本口径
A18: P01 | B18: 电子 | C18: =输入_持仓批次!E2+输入_持仓批次!E3+输入_持仓批次!E4 -> 5000 | D18: =输入_行情状态!C2 -> 32.8 | E18: =输入_行情状态!C2 -> 32.8 | F18: =C18*E18 -> 164000 | G18: =输入_持仓批次!E2*输入_持仓批次!F2+输入_持仓批次!E3*输入_持仓批次!F3+输入_持仓批次!E4*输入_持仓批次!F4 -> 196150 | H18: =F18-G18 -> -32150 | I18: 三批加权成本，当日买入1000股T+1不可卖
A19: P02 | B19: 计算机 | C19: =输入_持仓批次!E5 -> 3000 | D19: =输入_行情状态!C3 -> 58.4 | E19: =输入_行情状态!C3 -> 58.4 | F19: =C19*E19 -> 175200 | G19: =输入_持仓批次!E5*输入_持仓批次!F5 -> 162600 | H19: =F19-G19 -> 12600 | I19: 正常，8/14收盘跌停封单
A20: P03 | B20: 医药 | C20: =输入_持仓批次!E6 -> 8000 | D20: =输入_行情状态!C4 -> 9.62 | E20: =输入_行情状态!C4 -> 9.62 | F20: =C20*E20 -> 76960 | G20: =输入_持仓批次!E6*输入_持仓批次!F6 -> 82400 | H20: =F20-G20 -> -5440 | I20: 正常
A21: P04 | B21: 工业 | C21: =输入_持仓批次!E7 -> 6000 | D21: =输入_行情状态!C5 -> 12.35 | E21: =输入_行情状态!C5 -> 12.35 | F21: =C21*E21 -> 74100 | G21: =输入_持仓批次!E7*输入_持仓批次!F7 -> 71400 | H21: =F21-G21 -> 2700 | I21: 8/14停牌，用8/13价，不可卖
A22: P05 | B22: 计算机 | C22: =输入_持仓批次!E8 -> 2000 | D22: =输入_行情状态!C6 -> 105 | E22: =输入_行情状态!C6 -> 105 | F22: =C22*E22 -> 210000 | G22: =输入_持仓批次!E8*输入_持仓批次!F8 -> 164800 | H22: =F22-G22 -> 45200 | I22: 正常
A23: P06 | B23: 红利 | C23: =输入_持仓批次!E9 -> 10000 | D23: =输入_行情状态!C7 -> 2.88 | E23: =输入_行情状态!C7 -> 2.88 | F23: =C23*E23 -> 28800 | G23: =输入_持仓批次!E9*(输入_持仓批次!F9-0.8) -> 23000 | H23: =F23-G23 -> 5800 | I23: 成本已除息：(3.10-0.80)=2.30；股息8000元已入现金
A24: P07 | B24: 海外科技 | C24: =输入_持仓批次!E10 -> 10000 | D24: =输入_行情状态!C8 -> 15.3 | E24: =输入_行情状态!C8*0.92 -> 14.076 | F24: =C24*E24 -> 140760 | G24: =输入_持仓批次!E10*输入_持仓批次!F10*0.92 -> 150880 | H24: =F24-G24 -> -10120 | I24: 港币按0.92折人民币
A25: 合计 | F25: =SUM(F18:F24) -> 869820 | G25: =SUM(G18:G24) -> 851230 | H25: =SUM(H18:H24) -> 18590
A26: 校验：市值合计应=托管证券市值小计869,820
A28: 三、P01 可卖批次台账
A29: 批次 | B29: 批次日期 | C29: 数量 | D29: 单位成本 | E29: 批次成本 | F29: 是否可卖(8/17周一) | G29: 解冻/可卖起始日
A30: 批次1 | B30: 2026-05-10 | C30: 2500 | D30: 43.2 | E30: =C30*D30 -> 108000 | F30: 是 | G30: 历史批次，T+1早已可卖
A31: 批次2 | B31: 2026-07-02 | C31: 1500 | D31: 37.5 | E31: =C31*D31 -> 56250 | F31: 是 | G31: 历史批次，T+1早已可卖
A32: 批次3 | B32: 2026-08-14 | C32: 1000 | D32: 31.9 | E32: =C32*D32 -> 31900 | F32: 否 | G32: 当日买入，8/18(周二)起可卖
A33: 可卖合计(批次1+2) | C33: =C30+C31 -> 4000 | E33: =E30+E31 -> 164250 | F33: 应=可卖数量4000

Sheet 交易日历
A1: 交易日历（as-of 2026-08-14 周五 → 最迟行动日 2026-08-18）
A2: 日历日 | B2: 星期 | C2: 是否交易日 | D2: 可执行时段说明 | E2: 资金可用/可划转 | F2: 备注
A3: 2026-08-14 | B3: 周五 | C3: 是(已收盘) | D3: 截点17:00，盘后 | E3: — | F3: 数据截点；P02跌停封单、P04停牌
A4: 2026-08-15 | B4: 周六 | C4: 否 | D4: 休市 | E4: —
A5: 2026-08-16 | B5: 周日 | C5: 否 | D5: 休市 | E5: —
A6: 2026-08-17 | B6: 周一 | C6: 是 | D6: 09:30-11:30/13:00-15:00 | E6: 卖出成交款T+0可用、T+1可取 | F6: 客户确认净转出5万元；主路径执行日
A7: 2026-08-18 | B7: 周二 | C7: 是 | D7: 同上 | E7: 8/17卖出款已可划转 | F7: P01当日买入1000股解禁；后手/补执行窗口

Sheet 交易明细与费用
A1: 主路径交易明细、费用勾稽与扣费后实现盈亏（价格=8/14收盘，人民币元）
A3: 证券ID | B3: 操作 | C3: 数量 | D3: 原币价 | E3: RMB单价 | F3: 成交额RMB | G3: 费用口径 | H3: 费用RMB | I3: 净回笼RMB | J3: 扣费后实现盈亏
A4: P01 | B4: 卖 | C4: 4000 | D4: 32.8 | E4: 32.8 | F4: =C4*E4 -> 131200 | G4: A股:佣金max(额×0.03%,5)+印花税额×0.05% | H4: =MAX(F4*0.0003,5)+F4*0.0005 -> 104.96 | I4: =F4-H4 -> 131095.04 | J4: =I4-((2500*43.2+1500*37.5)) -> -33154.96
A5: P05 | B5: 卖 | C5: 300 | D5: 105 | E5: 105 | F5: =C5*E5 -> 31500 | G5: A股:同上 | H5: =MAX(F5*0.0003,5)+F5*0.0005 -> 25.2 | I5: =F5-H5 -> 31474.8 | J5: =I5-(300*82.4) -> 6754.8
A6: P07 | B6: 卖 | C6: 10000 | D6: 15.3 | E6: =15.3*0.92 -> 14.076 | F6: =C6*E6 -> 140760 | G6: 港股ETF综合费额×0.10% | H6: =F6*0.001 -> 140.76 | I6: =F6-H6 -> 140619.24 | J6: =I6-(10000*16.4*0.92) -> -10260.76
A7: 合计 | F7: =SUM(F4:F6) -> 303460 | H7: =SUM(H4:H6) -> 270.92 | I7: =SUM(I4:I6) -> 303189.08 | J7: =SUM(J4:J6) -> -36660.92
A9: 账户层面结果
A10: 项目 | B10: 公式/口径 | C10: 金额(元)
A11: 交易前总资产(托管净) | B11: 见公式 | C11: =输入_账户!B7 -> 1032660
A12: 减：本次卖出费用合计 | B12: 见公式 | C12: =交易明细与费用!H7 -> 270.92
A13: 交易后、提款前总资产 | B13: 见公式 | C13: =C11-C12 -> 1032389.1
A14: 人民币现金(交易后、提款前) | B14: 见公式 | C14: =输入_账户!B3+交易明细与费用!I7 -> 445689.08
A15: 减：客户确认净转出 | B15: 见公式 | C15: =-输入_账户!B9 -> -50000
A16: 人民币现金(提款后) | B16: 见公式 | C16: =C14+C15 -> 395689.08
A17: 提款后总资产(主路径分母) | B17: 见公式 | C17: =C13+C15 -> 982389.08

Sheet 方案对比
A1: 方案对比：未调整 vs 主路径(保守,P02不开板) vs P02开板替代（金额RMB，权重=各自口径总资产）
A3: 证券ID | B3: 未调整数量 | C3: 未调整市值 | D3: 未调整权重 | E3: 主路径后数量 | F3: 主路径后市值 | G3: 主路径后权重 | H3: 开板替代后数量 | I3: 开板替代后市值 | J3: 开板替代权重
A4: P01 | B4: 5000 | C4: =B4*32.8 -> 164000 | D4: =C4/1032660 -> 0.15881316 | E4: 1000 | F4: =E4*32.8 -> 32800 | G4: =F4/交易明细与费用!C17 -> 0.033387993 | H4: 2000 | I4: =H4*32.8 -> 65600 | J4: =I4/983900 -> 0.066673442
A5: P02 | B5: 3000 | C5: =B5*58.4 -> 175200 | D5: =C5/1032660 -> 0.16965894 | E5: 3000 | F5: =E5*58.4 -> 175200 | G5: =F5/交易明细与费用!C17 -> 0.17834074 | H5: 0 | I5: =H5*58.4 -> 0 | J5: =I5/983900 -> 0
A6: P03 | B6: 8000 | C6: =B6*9.62 -> 76960 | D6: =C6/1032660 -> 0.074525981 | E6: 8000 | F6: =E6*9.62 -> 76960 | G6: =F6/交易明细与费用!C17 -> 0.078339633 | H6: 8000 | I6: =H6*9.62 -> 76960 | J6: =I6/983900 -> 0.078219331
A7: P04 | B7: 6000 | C7: =B7*12.35 -> 74100 | D7: =C7/1032660 -> 0.071756435 | E7: 6000 | F7: =E7*12.35 -> 74100 | G7: =F7/交易明细与费用!C17 -> 0.075428363 | H7: 6000 | I7: =H7*12.35 -> 74100 | J7: =I7/983900 -> 0.075312532
A8: P05 | B8: 2000 | C8: =B8*105 -> 210000 | D8: =C8/1032660 -> 0.20335832 | E8: 1700 | F8: =E8*105 -> 178500 | G8: =F8/交易明细与费用!C17 -> 0.1816999 | H8: 1800 | I8: =H8*105 -> 189000 | J8: =I8/983900 -> 0.19209269
A9: P06 | B9: 10000 | C9: =B9*2.88 -> 28800 | D9: =C9/1032660 -> 0.027889141 | E9: 10000 | F9: =E9*2.88 -> 28800 | G9: =F9/交易明细与费用!C17 -> 0.029316287 | H9: 10000 | I9: =H9*2.88 -> 28800 | J9: =I9/983900 -> 0.029271267
A10: P07 | B10: 10000 | C10: =B10*15.3*0.92 -> 140760 | D10: =C10/1032660 -> 0.13630818 | E10: 0 | F10: =E10*15.3*0.92 -> 0 | G10: =F10/交易明细与费用!C17 -> 0 | H10: 8000 | I10: =H10*15.3*0.92 -> 112608 | J10: =I10/983900 -> 0.11445066
A11: 证券市值合计 | C11: =SUM(C4:C10) -> 869820 | F11: =SUM(F4:F10) -> 566360 | I11: =SUM(I4:I10) -> 547068
A13: 组合层面汇总（提款后口径）
A14: 口径 | B14: 未调整(仅提款) | C14: 主路径(保守) | D14: P02开板替代
A15: 科技主题市值 | B15: =C4+C5+C8+C10 -> 689960 | C15: =F4+F5+F8+F10 -> 386500 | D15: =I4+I5+I8+I10 -> 367208
A16: 高风险(内部等级高) | B16: =C4+C5+C8 -> 549200 | C16: =F4+F5+F8 -> 386500 | D16: =I4+I5+I8 -> 254600
A17: 外币资产(P07+美元现金) | B17: =C10+21540 -> 162300 | C17: =F10+21540 -> 21540 | D17: =I10+21540 -> 134148
A18: 现金类(人民币+美元折汇) | B18: =142500+21540-50000 -> 114040 | C18: =交易明细与费用!C16+21540 -> 417229.08 | D18: ≈见备注
A19: 口径分母(提款后总资产) | B19: =1032660-50000 -> 982660 | C19: =交易明细与费用!C17 -> 982389.08 | D19: ≈983,900(按相同费用口径估)
A20: 科技占比 | B20: =B15/B19 -> 0.70213502 | C20: =C15/C19 -> 0.39342864 | D20: =D15/983900 -> 0.37321679
A21: 高风险占比 | B21: =B16/B19 -> 0.55889117 | C21: =C16/C19 -> 0.39342864 | D21: =D16/983900 -> 0.25876613
A22: 外币占比 | B22: =B17/B19 -> 0.16516394 | C22: =C17/C19 -> 0.021926139 | D22: =D17/983900 -> 0.13634312
A23: 现金占比 | B23: =B18/B19 -> 0.11605235 | C23: =C18/C19 -> 0.42470859 | D23: —
A25: 说明：P02开板替代路径依赖P02周一能开板成交；若继续跌停则不可用，须走主路径。P04停牌不进入任何卖出路径。

Sheet 硬约束状态
A1: 硬约束状态表（当前=8/14收盘；主路径值=交易后+5万提款后；分母为提款后总资产）
A3: 约束名 | B3: 题面阈值 | C3: 当前值(8/14) | D3: 达标所需反解值(可执行整手) | E3: 主路径交易+提款后 | F3: 判定 | G3: 绑定/已消 | H3: 相邻一手检验 | I3: 对应规则号
A4: 最大单票(P05) | B4: ≤总资产20% | C4: =210000/1032660 -> 0.20335832 | D4: P05至少卖200股(300股留余量) | E4: =178500/交易明细与费用!C17 -> 0.1816999 | F4: 超限→达标 | G4: 绑定(单票) | H4: 少卖一手改卖100股→P05约20.3%，仍超限 | I4: R2
A5: 科技主题合计 | B5: ≤总资产40% | C5: =689960/1032660 -> 0.66813859 | D5: 科技市值须降到≤0.4×提款后总资产(约39.3万) | E5: =386500/交易明细与费用!C17 -> 0.39342864 | F5: 超限→达标 | G5: 绑定(最紧) | H5: P05少卖100股→科技约40.4%，超限 | I5: R1
A6: 内部高风险合计 | B6: ≤总资产45% | C6: =549200/1032660 -> 0.53183042 | D6: 高风险市值须降到≤0.45×提款后总资产(约44.2万) | E6: =386500/交易明细与费用!C17 -> 0.39342864 | F6: 超限→达标 | G6: 已被主路径卖出压回 | H6: 主路径后39.3%<45% | I6: R1
A7: 外币资产 | B7: ≤总资产15% | C7: =(140760+21540)/1032660 -> 0.15716693 | D7: P07至少卖1500份(留余量卖10000份) | E7: =21540/交易明细与费用!C17 -> 0.021926139 | F7: 超限→达标 | G7: 绑定(已通过退出P07解决) | H7: 主路径后外币仅余美元现金2.19% | I7: R3
A8: 人民币+现金类(提款后) | B8: ≥总资产10% | C8: =(142500+21540-50000)/(1032660-50000) -> 0.11605235 | D8: 现状即达标，无需为流动性卖出 | E8: =(交易明细与费用!C16+21540)/交易明细与费用!C17 -> 0.42470859 | F8: 达标 | G8: 不绑定 | H8: 提款后现金约42.5%，远高于10% | I8: R4

Sheet 条件规则
A1: if→then 交易纪律（数量按8/14价反解；周一按实际报价重算并向上取整手）
A3: 规则号 | B3: 触发条件(阈值+截止时点) | C3: 方向自检 | D3: 动作 | E3: 数量及口径(基准持仓) | F3: 目标权重 | G3: 预计费用/净回笼 | H3: 执行时点 | I3: 未成交后手 | J3: 交易后复核
A4: R1 | B4: 周一09:30起科技主题>40%或高风险>45%（按实时价重算） | C4: 下跌会降权重，故用其余持仓上涨/科技未达标作触发 | D4: 卖P01 4000股+P07 10000份+P05 300股 | E4: 累计总卖出量；基准8/14持仓(P015000/P0710000/P052000) | F4: 科技≤40%、高风险≤45% | G4: 费用约270.92元，净回笼约303,189元 | H4: 8/17盘中限价挂单 | I4: P05/P07若部分未成交，8/18用P01解禁1000股补；仍不足则P02开板时补卖 | J4: 收盘后重算科技/高风险/单票/外币，未达标的转R5
A5: R2 | B5: P05实时占比>20%（提款后口径） | C5: P05上涨才恶化，触发成立 | D5: 在R1中保证P05卖≥200股 | E5: 本路径追加300股P05；基准2000股 | F5: P05≤20% | G5: 含在R1费用内 | H5: 8/17 | I5: P05涨停无法卖则标记不可卖，改由其余科技卖出补差 | J5: P05≤20%
A6: R3 | B6: 外币资产>15%（P07+美元现金） | C6: P07上涨/人民币贬值才恶化 | D6: 卖P07 | E6: 本路径卖出10000份(全部)；基准10000份 | F6: 外币≤15% | G6: 含在R1费用内 | H6: 8/17 | I6: P07停牌/无法成交则当日外币无法压回，标记不可交易并监控 | J6: 外币≤15%
A7: R4 | B7: 客户确认8/17净转出50000元 | C7: 转出直接降低现金，方向成立 | D7: 从人民币现金划出50000元 | E7: 累计划出50000元 | F7: 现金类≥10% | G7: 无交易费用 | H7: 8/17(成交款可用后) | I7: 若卖出款未到账，先以账内142500现金支付，不足则延迟到8/18 | J7: 提款后现金≥10%
A8: R5 | B8: 8/17收盘仍有任一硬约束超限，或P02跌停未开 | C8: 继续恶化时升级 | D8: 不得加仓/回补/做T；8/18用P01解禁1000股重算补卖 | E8: 本阶段按缺口追加，整手向上取整 | F8: 全部≤限额 | G8: 按实际成交额重算 | H8: 8/18 | I8: P04仍停牌则其敞口冻结，不纳入可卖，仅监控 | J8: 复核回到限内前禁止扩大敞口
A9: R6 | B9: P04复牌日确定 | C9: 复牌后才可交易 | D9: 复牌首日按当时权重决定是否纳入卖出计划 | E9: 届时重算 | F9: — | G9: — | H9: 复牌日 | I9: 复牌补跌先不接，待价格稳定再评估 | J9: 复牌后权重与流动性

Sheet 假设与缺失
A1: 假设与缺失清单（勾稽残差、口径与待确认项）
A3: 条目 | B3: 类型 | C3: 来源/推断依据 | D3: 影响哪些结论 | E3: 补齐后需重算什么
A4: 托管锚总资产1,032,660作为主分母 | B4: 已确认事实 | C4: 869820+142500+3000×7.18−1200，逐项勾稽一致 | D4: 全部权重与限额判定 | E4: —
A5: 组合经理手工总资产1,029,000 | B5: 仍缺证据 | C5: 较托管锚少3,660元，附件未给差异来源(估值时点/费用预提/折算口径均可能) | D5: 若改用手工锚，各权重约+0.35pp，超限方向不变 | E5: 取得差异来源后重算权重；外币15.72%最敏感
A6: P06成本按除息后重建2.30 | B6: 合理推断 | C6: 每份派0.80，3.10−0.80=2.30；除息参考价2.88仅作涨跌幅参照 | D6: P06浮动盈亏由账面-2200修正为含息+5800 | E6: 现金股息8000元已在142500现金内，到账日需确认
A7: P07按0.92折人民币 | B7: 合理推断 | C7: 附件P07说明给定0.92 | D7: P07市值、外币敞口 | E7: 实际结算币种与到账汇率需券商确认
A8: P04按8/13价12.35估值 | B8: 仍缺证据 | C8: 8/14停牌、复牌日未定 | D8: P04市值74100(7.5%)冻结，不可卖 | E8: 复牌后按市价重估与权重
A9: P02周一开板假设 | B9: 情景假设 | C9: 主路径保守假设其不开板；开板为替代路径 | D9: 决定卖P02还是卖P01/P05 | E9: 周一开盘看涨跌停状态再选路径
A10: 卖出成交款T+0可用/T+1可取 | B10: 合理推断 | C10: A股通行结算 | D10: 5万提款时点 | E10: 若遇交收延迟，提款顺延至8/18
A11: 不融资融券、无场外杠杆 | B11: 已确认事实 | C11: 账户授权说明 | D11: 风险预算口径 | E11: —

Sheet 自检回执
A1: 交付自检回执（逐行填值，不打勾）
A3: 自检项 | B3: 填写值
A4: 交付清单 | B4: 声明1件/实际1件：组合持仓诊断与交易纪律.xlsx（内含输入快照、勾稽、日历、硬约束、方案、交易明细、规则、假设、自检）
A5: 交付主工件是否为文件 | B5: 是，.xlsx工作簿
A6: 工作簿可复算抽查 | B6: 勾稽!C9托管锚=869820+142500+3000×7.18−1200=1,032,660；交易明细!H7费用合计公式=SUM(H4:H6)；已用LibreOffice重算无#REF/#DIV
A7: 占比分母 | B7: 权重分母=提款后托管净总资产(主路径≈982,389)；当前值分母=8/14托管净1,032,660
A8: 最紧约束 | B8: 科技主题；当前66.81%；限额40%；反解须压降科技市值约29.7万；对应R1
A9: 分解型占比加总 | B9: 各标的权重之和=100%；科技/高风险/行业分解加总已核对(见方案对比)
A10: 最不利情景 | B10: P02继续跌停、P04停牌：主路径仍可压回全部限额(科技39.34%)
A11: 日期来源 | B11: 行动日8/17(周一)、后手8/18(周二)均取自交易日历表
A12: 数量口径 | B12: R1为累计总卖出量；基准8/14持仓；R5为本阶段追加量
A13: 费用口径 | B13: 隐含费率≈270.92/303460=0.0893%，与题设(佣金0.03%+印花0.05%+港股0.10%加权)一致
A14: 跨文件一致 | B14: 科技占比：决策摘要/硬约束/方案对比均=39.34%；P05=18.17%；现金=42.47%
A15: 非执行声明 | B15: 本工作簿仅调仓前分析，不代表已下单，不保证回本或收益
