Workbook

Sheet 输入快照
A1: 输入快照（as-of 2026-09-10 14:20，基准币种人民币）
A3: 项目 | B3: 值 | C3: 单位/说明 | D3: 来源材料
A4: 人民币可用现金 | B4: 220000 | C4: 元 | D4: K01 券商导出
A5: 港币可用现金 | B5: 60000 | C5: 港币 | D5: K02
A6: 即期汇率 | B6: 0.92 | C6: 人民币/港币 | D6: K02
A7: 冻结申购款 | B7: 16000 | C7: 元（9/12解冻） | D7: K03
A8: 券商显示总资产 | B8: 1009200 | C8: 元 | D8: K04
A9: A 铜资源股 现价 | B9: 49.5 | C9: 元/股 | D9: H01/M01
A10: A 总持股 | B10: 8000 | C10: 股（含当日买2000） | D10: H01
A11: A 当日可卖 | B11: 6000 | C11: 股（T+1锁2000） | D11: H01/T01
A12: B 光模块股 现价 | B12: 120 | C12: 元/股（9/9收盘，9/10停牌） | D12: H02/M02
A13: B 总持股 | B13: 1800 | C13: 股（10转5后） | D13: H02/CA01
A14: B 当日可卖 | B14: 0 | C14: 股（停牌不可成交） | D14: T02
A15: C 新能源股 现价 | B15: 60 | C15: 元/股（当日跌停） | D15: H03/M03
... A20: 卖出综合费率(假设) | B20: 0.001 | C20: 成交额%（佣金+过户+印花+滑点，D03缺个性化税率） | D20: 本方案假设

Sheet 持仓勾稽
A1: 持仓勾稽：数量、重建成本、人民币市值、未实现盈亏
A3: 标的 | B3: 总数量 | C3: 可卖数量 | D3: 重建成本(元) | E3: 调整后单位成本 | F3: 人民币市值 | G3: 未实现盈亏 | H3: 盈亏率 | I3: 采用记录/冲突说明
A4: 铜资源股A | B4: ='输入快照'!B10 | C4: ='输入快照'!B11 | D4: 384429 | E4: =D4/B4 | F4: =B4*'输入快照'!B9 | G4: =F4-D4 | H4: =G4/D4 | I4: 采用L01+L02+L03成交确认单重建；客户口述49.25(D02)与OCR均不采用
A5: 光模块股B | B5: ='输入快照'!B13 | C5: 0 | D5: 180360 | E5: =D5/B5 | F5: =B5*'输入快照'!B12 | G5: =F5-D5 | H5: =G5/D5 | I5: L04成本经CA01 10转5除权，总成本不变；D01 OCR 1200股@150.15为转增前截图，不采用
A6: 新能源股C | B6: ='输入快照'!B16 | C6: ='输入快照'!B17 | D6: 68102 | E6: =D6/B6 | F6: =B6*'输入快照'!B15 | G6: =F6-D6 | H6: =G6/D6 | I6: L05成交确认单重建
A7: 恒生科技ETF D | B7: ='输入快照'!B19 | C7: ='输入快照'!B19 | D7: 52852.8 | E7: =D7/B7 | F7: =B7*'输入快照'!B18*'输入快照'!B6 | G7: =F7-D7 | H7: =G7/D7 | I7: L06/L07按成交日汇率0.94/0.93折人民币成本
A8: 证券市值合计 | F8: =SUM(F4:F7)
A9: 人民币现金 | F9: ='输入快照'!B4
A10: 港币现金折人民币 | F10: ='输入快照'!B5*'输入快照'!B6
A11: 冻结申购款 | F11: ='输入快照'!B7
A12: 勾稽总资产 | F12: =F8+F9+F10+F11
A13: 券商显示总资产(K04) | F13: ='输入快照'!B8
A14: 勾稽残差 | F14: =F12-'输入快照'!B8

Sheet 交易日历
A1: 交易日历（从as-of到计划覆盖的3个交易日）
A3: 日历日 | B3: 星期 | C3: 是否交易日 | D3: 可执行时段说明 | E3: 资金可用/可划转 | F3: 备注
A4: 2026-09-10 | B4: 周四 | C4: 是 | D4: 14:20在交易时段内，至15:00收盘 | E4: 人民币现金可用；港币需换汇 | F4: 审阅时点；A当日买2000股T+1锁定；B停牌；C跌停
A5: 2026-09-11 | B5: 周五 | C5: 是 | D5: 全日交易时段 | E5: A的2000股T+1解冻可卖 | F5: B预计仍停牌（重大重组，≤5个交易日）；C观察是否打开跌停
A6: 2026-09-12 | B6: 周六 | C6: 否 | D6: 非交易日 | E6: 冻结申购款名义解冻日，但非交易日不可执行 | F6: 顺延
A7: 2026-09-13 | B7: 周日 | C7: 否 | D7: 非交易日 | E7: 顺延 | F7: 顺延
A8: 2026-09-14 | B8: 周一 | C8: 是 | D8: 全日交易时段 | E8: 冻结16000元转为可用；全部持仓可卖（除B复牌前） | F8: B停牌可能仍在（预计最晚9/17复牌）

Sheet 硬约束状态
A1: 硬约束状态表（阈值/当前值/反解达标整手/主方案后值/判定）
A3: 约束名 | B3: 题面阈值 | C3: 当前值 | D3: 达标所需反解值(可执行整手) | E3: 主方案交易后值 | F3: 用户偏好方案值 | G3: 判定 | H3: 绑定/已被消除 | I3: 少一手检验 | J3: 规则号
A4: 风险资产仓位 | B4: ≤70% | C4: 71.15% | D4: 卖A≥300股 | E4: 45.16% | F4: 71.15%(不动) | G4: 超限→达标 | H4: 被主方案消除 | I4: 卖200股仍71.2%超限 | J4: R1
A5: 单一标的A | B5: ≤22% | C5: 39.24% | D5: 卖A≥3600股 | E5: 13.25% | F5: 39.24%(偏好保留A) | G5: 超限→达标 | H5: 绑定(但被更紧的R1覆盖) | I5: 卖3500股=22.08%仍超限 | J5: R1
A6: 主题(铜资源=A) | B6: ≤35% | C6: 39.24% | D6: 卖A≥900股 | E6: 13.25% | F6: 39.24% | G6: 超限→达标 | H6: 被主方案消除 | I6: 卖800股=39.6%仍超限 | J6: R1
A7: 未对冲外币敞口 | B7: ≤25% | C7: 10.03% | D7: 无需卖出 | E7: 10.03% | F7: 10.03% | G7: 达标 | H7: - | I7: - | J7: -
A8: 可自由使用现金 | B8: ≥25% | C8: 27.27% | D8: 无需卖出 | E8: 53.30% | F8: 27.27% | G8: 达标(偏紧) | H8: - | I8: - | J8: -
A9: 一周压力损失 | B9: ≤6% | C9: 9.07% | D9: 卖A≥5300股 | E9: 5.95% | F9: 9.07% | G9: 超限→达标 | H9: 最紧约束(绑定) | I9: 卖5200股=6.01%仍超限 | J9: R1
A10: 单一标的B | B10: ≤22% | C10: 21.40% | D10: 无需(停牌不可卖) | E10: 21.41% | F10: 21.40% | G10: 达标(贴近) | H10: 复牌后监控 | I10: - | J10: R3

Sheet 压力情景
A1: 一周压力情景 S01 逐日/逐项复合（现金与冻结面值不变）
A3: 项目 | B3: 冲击 | C3: 原人民币市值 | D3: 损失额 | E3: 说明
A4: 铜资源股A | B4: -12% | C4: 396000 | D4: 47520 | E4: 实时价49.50，可成交
A5: 光模块股B | B5: -15% | C5: 216000 | D5: 32400 | E5: 停牌，按9/9收盘120元计，复牌价未知
A6: 新能源股C | B6: -10% | C6: 60000 | D6: 6000 | E6: 跌停价60.00
A7: 恒生科技ETF D | B7: 价-8%+港币-2% | C7: 46000 | D7: 4526.4 | E7: 港币价10→9.20，汇率0.92→0.9016
A8: 港币现金 | B8: 港币-2% | C8: 55200 | D8: 1104 | E8: 60000港币×0.92×2%
A9: 合计 | C9: 773200 | D9: 91550.4 | E9: 损失率9.07% > 6%阈值
A10: 主方案卖A5300股后压力损失 | D10: 60068.4 | E10: 剩余A市值133650×12%+B32400+C6000+D4526.4+港币1104=60068.4；损失率5.95%≤6%
A11: 最不利情景判定 | E11: S01统一冲击即题面唯一情景；取其值9.07%判定FAIL，主方案后5.95%判定PASS

Sheet 方案对比
A1: 方案对比：未调整 / 用户偏好 / 合规减仓(主方案)
A3: 指标 | B3: 未调整现状 | C3: 用户偏好(尽量保留A、B) | D3: 合规减仓主方案(卖A5300股)
A4: 卖出A股数 | B4: 0 | C4: 0 | D4: 5300股(53手，来自当日可卖6000股)
A5: A剩余市值(元) | B5: 396000 | C5: 396000 | D5: 133650
A6: A权重 | B6: 39.24% | C6: 39.24% | D6: 13.25%
A7: 风险资产权重 | B7: 71.15% | C7: 71.15% | D7: 45.16%
A8: B权重 | B8: 21.40% | C8: 21.40% | D8: 21.41%
A9: 自由现金权重 | B9: 27.27% | C9: 27.27% | D9: 53.30%
A10: 外币敞口 | B10: 10.03% | C10: 10.03% | D10: 10.03%
A11: 压力损失率 | B11: 9.07% | C11: 9.07% | D11: 5.95%
A12: 是否全部硬约束达标 | B12: 否(3项超限) | C12: 否(3项超限) | D12: 是
A13: 与偏好冲突 | B13: - | C13: - | D13: 主方案按硬约束卖出A，偏离‘保留A’偏好；B停牌不可卖故保留

Sheet 交易明细
A1: 主方案交易明细（卖A 5300股，限价区间，整手）
A3: 项目 | B3: 数值 | C3: 公式/口径
A4: 卖出标的 | B4: 铜资源股A
A5: 卖出数量(股) | B5: 5300 | C5: 53手×100；来自当日可卖6000股(批次1+2)
A6: 委托价格区间 | B6: 49.30–49.50元 | C6: 贴近现价49.50，高于近端支撑46.80
A7: 成交额(元) | B7: 262350 | C7: 5300×49.50
A8: 卖出综合费用(元) | B8: 262.35 | C8: 成交额×0.10%(假设，D03缺个性化税率)
A9: 净回笼人民币(元) | B9: 262087.65 | C9: 成交额-费用
A10: 卖出部分成本(元) | B10: 247787.08 | C10: 可卖批次成本280325×(5300/6000)
A11: 实现盈亏(扣费后,元) | B11: 14300.57 | C11: 262350-247787.08-262.35
A12: 剩余A股数 | B12: 2700 | C12: 8000-5300(含T+1批次2000)
A13: 剩余A成本(元) | B13: 136641.92 | C13: 384429-247787.08
A14: 交易后人民币现金(元) | B14: 482087.65 | C14: 220000+262087.65
A15: 交易后总资产(元) | B15: 1008937.7 | C15: 1009200-262.35费用

Sheet 条件规则
A1: if→then 交易纪律表（不代客下单、不保证成交）
A3: 规则号 | B3: 触发条件(阈值+截止时点) | C3: 方向自检 | D3: 动作 | E3: 数量及口径(基准持仓) | F3: 目标权重 | G3: 费用与净回笼 | H3: 执行时点 | I3: 未成交后手 | J3: 交易后复核
A4: R1 | B4: 9/10 14:20–14:55，A在49.00–50.00元区间有连续买盘、未涨停/未停牌 | C4: 下跌不触发本规则；本规则在A仍可成交时压降超限敞口，方向正确 | D4: 限价卖出A | E4: 累计总卖出5300股(53手)；基准持仓8000股，来自当日可卖6000股 | F4: A降至13.25% | G4: 费用262.35，净回笼262087.65 | H4: 9/10剩余时段 | I4: 若14:55未全成，未成交量顺延9/11继续限价；9/11另2000股T+1解冻，可卖量充足 | J4: 复核A权重≤22%、压力损失≤6%
A5: R2 | B5: 若R1当日未全部成交，9/11开盘后A仍在48.50–50.50区间 | C5: 继续压降，方向正确 | D5: 继续限价卖出A | E5: 本阶段追加=未成交余额(累计仍5300股) | F5: A降至13.25% | G5: 按同费率 | H5: 9/11 | I5: 若A涨停无法卖，改卖C(若打开跌停反弹至62元上方)或D(港币)；但C/D冲击系数低于A，须复核压力仍≤6% | J5: 复核成交笔数与回笼现金
A6: R3 | B6: B复牌首日(预计不早于9/17)，若B涨幅使B权重>22% | C6: 上涨使B权重恶化，方向正确 | D6: 限价卖出B | E6: 累计卖出至B权重≤20%(约1800股中超出部分) | F6: B≤20% | G6: 按同费率 | H6: 复牌后首个可交易日 | I6: 复牌若跌停则挂单待成交，不追卖 | J6: 复核B权重与停牌缺口
A7: R4 | B7: C若打开跌停且反弹至62元上方(压力位66元下方) | C7: 反弹提供流动性，方向正确 | D7: 限价卖出C(可选) | E7: 1000股(全部) | F7: C降至0 | G7: 按同费率 | H7: 9/11起任意交易日 | I7: 若仍跌停无买盘，不强行挂单，保留 | J7: 复核组合现金
A8: R5 | B8: 任意时刻：任一硬约束回到限内前，禁止加仓/回补/做T | C8: 约束恶化时扩大敞口错误，方向正确 | D8: 暂停买入 | E8: 0 | F8: - | G8: - | H8: 持续 | I8: - | J8: -
A9: R6 | B9: 9/14冻结16000元解冻到账后 | C9: 现金增加，不影响权重 | D9: 仅记账，不自动交易 | E9: 0 | F9: - | G9: - | H9: 9/14 | I9: - | J9: 复核自由现金≥25%

Sheet 核验
A1: 核验表：被核验指标｜取值单元格｜公式原文｜重算值｜与正文一致
A3: 被核验指标 | B3: 取值所在单元格 | C3: 公式原文 | D3: 重算值 | E3: 与正文是否一致
A4: 勾稽总资产-券商总资产残差 | B4: 持仓勾稽!F14 | C4: =F14 | D4: 0 | E4: 是(0，完全勾稽)
A5: 证券市值合计 | B5: 持仓勾稽!F8 | C5: =SUM(F4:F7) | D5: 718000 | E5: 是
A6: A未实现盈亏 | B6: 持仓勾稽!G4 | C6: =F4-D4 | D6: 11571 | E6: 是
A7: B未实现盈亏 | B7: 持仓勾稽!G5 | C7: =F5-D5 | D7: 35640 | E7: 是
A8: C未实现盈亏 | B8: 持仓勾稽!G6 | C8: =F6-D6 | D8: -8102 | E8: 是
A9: D未实现盈亏 | B9: 持仓勾稽!G7 | C9: =F7-D7 | D9: -6852.8 | E9: 是
A10: 风险资产权重 | B10: 硬约束状态!C4 | C10: 718000/1009200 | D10: 0.7115 | E10: 是
A11: 压力损失率(现状) | B11: 压力情景!D9 | C11: 91550.4/1009200 | D11: 0.0907 | E11: 是
A12: 主方案后压力损失率 | B12: 压力情景!D10 | C12: 60068.4/1008937.65 | D12: 0.0595 | E12: 是
A13: 风险贡献加总 | B13: (脚本计算) | C13: Σ RC_i | D13: 1 | E13: 是(=100%)
A14: 费用隐含费率 | B14: 交易明细!B6/B5 | C14: 262.35/262350 | D14: 0.001 | E14: 是(=假设0.10%)
