Workbook

Sheet 封面与口径
A1: 组合持仓诊断与交易纪律（调仓前分析稿）
A3: 资料截点 (as-of) | B3: 2026-08-14 17:00 北京时间
A4: 决策窗口 | B4: 2026-08-17（周一）客户确认净转出 50,000 元，同日起可执行调仓
A5: 基准币种 | B5: 人民币元（HKD/USD 按截点汇率折算）
A6: 美元兑人民币汇率 | B6: 7.18
A7: 港币兑人民币汇率 | B7: 0.92
A8: 采用的总资产口径（主） | B8: 托管系统口径 = 证券市值 869,820 + RMB现金 142,500 + USD现金 3,000×7.18 − 待扣费用 1,200 = 1,032,660
A9: 组合经理手工记录 | B9: 1029000
A10: 两口径差额（托管 − 手工） | B10: =1032660-B9 -> 3660
A11: 未决残差说明 | B11: 托管系统 1,032,660 可与明细逐项勾稽；PM 手工 1,029,000 少 3,660 元，附件未给出差异来源。本稿主口径采用托管数，差额计入‘假设与缺失’，不用其他资产抹平。
A12: 本周已确认净流出 | B12: 50000
A13: 可用状态 | B13: 不融资、不融券、无场外杠杆；仅调仓前分析，不代表已下单

Sheet 输入快照-账户
A1: 输入快照：账户汇总（原样保留，蓝色为附件原值）
A2: 字段 | B2: 数值 | C2: 币种或单位 | D2: 记录时间 | E2: 来源
A3: 证券市值小计 | B3: 869820 | C3: 人民币元 | D3: 2026-08-14 15:05 | E3: 托管系统
A4: 人民币可用现金 | B4: 142500 | C4: 人民币元 | D4: 2026-08-14 15:05 | E4: 资金系统
A5: 美元现金 | B5: 3000 | C5: 美元 | D5: 2026-08-14 15:05 | E5: 资金系统
A6: 美元兑人民币折算汇率 | B6: 7.18 | C6: 人民币/美元 | D6: 2026-08-14 15:00 | E6: 内部估值表
A7: 待扣费用 | B7: 1200 | C7: 人民币元 | D7: 2026-08-14 15:05 | E7: 托管系统
A8: 账户总资产记录 | B8: 1032660 | C8: 人民币元 | D8: 2026-08-14 15:05 | E8: 托管系统
A9: 组合经理手工记录总资产 | B9: 1029000 | C9: 人民币元 | D9: 2026-08-14 15:10 | E9: 组合工作表
A10: 本周计划净流出 | B10: 50000 | C10: 人民币元 | D10: 2026-08-17 | E10: 客户已确认

Sheet 输入快照-持仓批次
A1: 输入快照：持仓批次台账（原样保留）
A2: 证券ID | B2: 证券类型 | C2: 行业或主题 | D2: 批次日期 | E2: 数量 | F2: 单位成本 | G2: 成本币种 | H2: 是否当日买入 | I2: 当前价格 | J2: 价格币种
A3: P01 | B3: A股 | C3: 电子 | D3: 2026-05-10 | E3: 2500 | F3: 43.2 | G3: 人民币 | H3: 否 | I3: 32.8 | J3: 人民币
A4: P01 | B4: A股 | C4: 电子 | D4: 2026-07-02 | E4: 1500 | F4: 37.5 | G4: 人民币 | H4: 否 | I4: 32.8 | J4: 人民币
A5: P01 | B5: A股 | C5: 电子 | D5: 2026-08-14 | E5: 1000 | F5: 31.9 | G5: 人民币 | H5: 是 | I5: 32.8 | J5: 人民币
A6: P02 | B6: A股 | C6: 计算机 | D6: 2026-03-18 | E6: 3000 | F6: 54.2 | G6: 人民币 | H6: 否 | I6: 58.4 | J6: 人民币
A7: P03 | B7: A股 | C7: 医药 | D7: 2026-04-11 | E7: 8000 | F7: 10.3 | G7: 人民币 | H7: 否 | I7: 9.62 | J7: 人民币
A8: P04 | B8: A股 | C8: 工业 | D8: 2026-01-20 | E8: 6000 | F8: 11.9 | G8: 人民币 | H8: 否 | I8: 12.35 | J8: 人民币
A9: P05 | B9: A股 | C9: 计算机 | D9: 2025-12-05 | E9: 2000 | F9: 82.4 | G9: 人民币 | H9: 否 | I9: 105 | J9: 人民币
A10: P06 | B10: 境内ETF | C10: 红利 | D10: 2026-02-06 | E10: 10000 | F10: 3.1 | G10: 人民币 | H10: 否 | I10: 2.88 | J10: 人民币
A11: P07 | B11: 港股ETF | C11: 海外科技 | D11: 2026-06-16 | E11: 10000 | F11: 16.4 | G11: 港币 | H11: 否 | I11: 15.3 | J11: 港币

Sheet 输入快照-可交易状态
A1: 输入快照：行情与可交易状态（原样保留）
A2: 证券ID | B2: 市场 | C2: 最新价格 | D2: 币种 | E2: 价格时间 | F2: 交易状态 | G2: 涨跌停状态 | H2: 当日买入数量 | I2: 可卖数量 | J2: 最小交易单位 | K2: 20日均额_万元 | L2: 说明
A3: P01 | B3: 沪深 | C3: 32.8 | D3: 人民币 | E3: 2026-08-14 15:00 | F3: 正常 | G3: 无 | H3: 1000 | I3: 4000 | J3: 100 | K3: 8600 | L3: 当日买入部分按T+1管理
A4: P02 | B4: 沪深 | C4: 58.4 | D4: 人民币 | E4: 2026-08-14 15:00 | F4: 正常 | G4: 跌停 | H4: 0 | I4: 3000 | J4: 100 | K4: 2100 | L4: 收盘封单，次日成交不确定
A5: P03 | B5: 沪深 | C5: 9.62 | D5: 人民币 | E5: 2026-08-14 15:00 | F5: 正常 | G5: 无 | H5: 0 | I5: 8000 | J5: 100 | K5: 4700
A6: P04 | B6: 沪深 | C6: 12.35 | D6: 人民币 | E6: 2026-08-13 15:00 | F6: 停牌 | G6: 不适用 | H6: 0 | I6: 0 | J6: 100 | K6: 900 | L6: 8月14日全天停牌，复牌日未确定
A7: P05 | B7: 沪深 | C7: 105 | D7: 人民币 | E7: 2026-08-14 15:00 | F7: 正常 | G7: 无 | H7: 0 | I7: 2000 | J7: 100 | K7: 12800
A8: P06 | B8: 沪深 | C8: 2.88 | D8: 人民币 | E8: 2026-08-14 15:00 | F8: 正常 | G8: 无 | H8: 0 | I8: 10000 | J8: 100 | K8: 56000 | L8: 8/12每份现金分配0.80；8/11未调收盘3.68，调整后参考价2.88
A9: P07 | B9: 香港 | C9: 15.3 | D9: 港币 | E9: 2026-08-14 16:00 | F9: 正常 | G9: 无 | H9: 0 | I9: 10000 | J9: 500 | K9: 12500 | L9: 港币兑人民币估值汇率0.92

Sheet 输入快照-风险暴露
A1: 输入快照：风险暴露（原样保留）
A2: 证券ID | B2: 风险分类 | C2: 组合分组 | D2: 近60日波动率 | E2: 内部风险等级 | F2: 与P05相关系数 | G2: 是否外币暴露
A3: P01 | B3: 成长 | C3: 科技 | D3: 0.38 | E3: 高 | F3: 0.72 | G3: 否
A4: P02 | B4: 成长 | C4: 科技 | D4: 0.44 | E4: 高 | F4: 0.81 | G4: 否
A5: P03 | B5: 防御 | C5: 医药 | D5: 0.25 | E5: 中 | F5: 0.18 | G5: 否
A6: P04 | B6: 周期 | C6: 工业 | D6: 0.29 | E6: 中 | F6: 0.22 | G6: 否
A7: P05 | B7: 成长 | C7: 科技 | D7: 0.46 | E7: 高 | F7: 1 | G7: 否
A8: P06 | B8: 防御 | C8: 红利 | D8: 0.17 | E8: 低 | F8: -0.05 | G8: 否
A9: P07 | B9: 成长 | C9: 科技 | D9: 0.31 | E9: 中高 | F9: 0.64 | G9: 是

Sheet 持仓勾稽
A1: 持仓勾稽、批次成本、浮动盈亏与权重（as-of 2026-08-14）
A3: 口径锚（蓝色为附件原值）
A4: 人民币可用现金 | B4: ='输入快照-账户'!B4 -> 142500
A5: 美元现金(USD) | B5: ='输入快照-账户'!B5 -> 3000
A6: 美元兑人民币 | B6: ='输入快照-账户'!B6 -> 7.18
A7: 待扣费用 | B7: ='输入快照-账户'!B7 -> 1200
A8: 采用总资产(托管系统) | B8: ='输入快照-账户'!B8 -> 1032660
A9: PM手工记录总资产 | B9: ='输入快照-账户'!B9 -> 1029000
A10: 本周已确认净流出 | B10: ='输入快照-账户'!B11 -> 0
A12: 证券ID | B12: 行业/分组 | C12: 风险等级 | D12: 币种 | E12: 总数量 | F12: 现价(原币) | G12: 折算汇率 | H12: 现价(RMB) | I12: 总成本(RMB) | J12: 市值(RMB) | K12: 浮动盈亏(RMB) | L12: 权重 | M12: 周一可卖 | N12: 状态/备注
A13: P01 | B13: 电子/科技 | C13: 高 | D13: 人民币 | E13: ='输入快照-持仓批次'!E3+'输入快照-持仓批次'!E4+'输入快照-持仓批次'!E5 -> 5000 | F13: ='输入快照-可交易状态'!C3 -> 32.8 | G13: 1 | H13: =F13*G13 -> 32.8 | I13: ='输入快照-持仓批次'!E3*'输入快照-持仓批次'!F3+'输入快照-持仓批次'!E4*'输入快照-持仓批次'!F4+'输入快照-持仓批次'!E5*'输入快照-持仓批次'!F5 -> 196150 | J13: =E13*H13 -> 164000 | K13: =J13-I13 -> -32150 | L13: =J13/$B$8 -> 0.15881316 | M13: ='输入快照-可交易状态'!I3+'输入快照-可交易状态'!H3 -> 5000 | N13: 含8/14当日买入1000股，周一T+1解冻后可卖
A14: P02 | B14: 计算机/科技 | C14: 高 | D14: 人民币 | E14: ='输入快照-持仓批次'!E6 -> 3000 | F14: ='输入快照-可交易状态'!C4 -> 58.4 | G14: 1 | H14: =F14*G14 -> 58.4 | I14: ='输入快照-持仓批次'!E6*'输入快照-持仓批次'!F6 -> 162600 | J14: =E14*H14 -> 175200 | K14: =J14-I14 -> 12600 | L14: =J14/$B$8 -> 0.16965894 | M14: ='输入快照-可交易状态'!I4 -> 3000 | N14: 8/14收盘跌停封单，周一成交不确定
A15: P03 | B15: 医药 | C15: 中 | D15: 人民币 | E15: ='输入快照-持仓批次'!E7 -> 8000 | F15: ='输入快照-可交易状态'!C5 -> 9.62 | G15: 1 | H15: =F15*G15 -> 9.62 | I15: ='输入快照-持仓批次'!E7*'输入快照-持仓批次'!F7 -> 82400 | J15: =E15*H15 -> 76960 | K15: =J15-I15 -> -5440 | L15: =J15/$B$8 -> 0.074525981 | M15: ='输入快照-可交易状态'!I5 -> 8000 | N15: 正常
A16: P04 | B16: 工业 | C16: 中 | D16: 人民币 | E16: ='输入快照-持仓批次'!E8 -> 6000 | F16: ='输入快照-可交易状态'!C6 -> 12.35 | G16: 1 | H16: =F16*G16 -> 12.35 | I16: ='输入快照-持仓批次'!E8*'输入快照-持仓批次'!F8 -> 71400 | J16: =E16*H16 -> 74100 | K16: =J16-I16 -> 2700 | L16: =J16/$B$8 -> 0.071756435 | M16: ='输入快照-可交易状态'!I6 -> 0 | N16: 停牌，可卖0；价格为8/13收盘
A17: P05 | B17: 计算机/科技 | C17: 高 | D17: 人民币 | E17: ='输入快照-持仓批次'!E9 -> 2000 | F17: ='输入快照-可交易状态'!C7 -> 105 | G17: 1 | H17: =F17*G17 -> 105 | I17: ='输入快照-持仓批次'!E9*'输入快照-持仓批次'!F9 -> 164800 | J17: =E17*H17 -> 210000 | K17: =J17-I17 -> 45200 | L17: =J17/$B$8 -> 0.20335832 | M17: ='输入快照-可交易状态'!I7 -> 2000 | N17: 正常；PM‘暂不减持’未获批准
A18: P06 | B18: 红利 | C18: 低 | D18: 人民币 | E18: ='输入快照-持仓批次'!E10 -> 10000 | F18: ='输入快照-可交易状态'!C8 -> 2.88 | G18: 1 | H18: =F18*G18 -> 2.88 | I18: ='输入快照-持仓批次'!E10*'输入快照-持仓批次'!F10-10000*0.8 -> 23000 | J18: =E18*H18 -> 28800 | K18: =J18-I18 -> 5800 | L18: =J18/$B$8 -> 0.027889141 | M18: ='输入快照-可交易状态'!I8 -> 10000 | N18: 8/12每份分红0.80，成本已重建(3.10-0.80=2.30)
A19: P07 | B19: 海外科技 | C19: 中高 | D19: 港币 | E19: ='输入快照-持仓批次'!E11 -> 10000 | F19: ='输入快照-可交易状态'!C9 -> 15.3 | G19: 0.92 | H19: =F19*G19 -> 14.076 | I19: ='输入快照-持仓批次'!E11*'输入快照-持仓批次'!F11*0.92 -> 150880 | J19: =E19*H19 -> 140760 | K19: =J19-I19 -> -10120 | L19: =J19/$B$8 -> 0.13630818 | M19: ='输入快照-可交易状态'!I9 -> 10000 | N19: 港币计价，汇率0.92；500份整手
A20: 合计 | I20: =SUM(I13:I19) -> 851230 | J20: =SUM(J13:J19) -> 869820 | K20: =SUM(K13:K19) -> 18590 | L20: =SUM(L13:L19) -> 0.84231015
A22: 勾稽检验
A23: 证券市值合计 vs 托管‘证券市值小计869820’ | B23: =J20 -> 869820 | C23: =IF(ROUND(B23-869820,2)=0,"一致","差异"+TEXT(B23-869820,"0")) -> 一致
A24: RMB现金+USD折算+证券市值−待扣费用 | B24: =B4+B5*B6+J20-B7 -> 1032660 | C24: =IF(ROUND(B24-B8,2)=0,"一致","差异"+TEXT(B24-B8,"0")) -> 一致
A25: 两口径总资产差额(托管−PM手工) | B25: =B8-B9 -> 3660
A26: 证券权重合计(应≈证券占比) | B26: =L20 -> 0.84231015

Sheet 交易日历
A1: 交易日历（as-of 2026-08-14 周五 → 最迟行动日）
A3: 日历日 | B3: 星期 | C3: 是否交易日 | D3: 可执行时段 | E3: 资金可划转 | F3: 备注
A4: 2026-08-14 | B4: 周五 | C4: 是(已收盘) | D4: 15:00后不可交易 | E4: 已结算 | F4: 截点；P02跌停、P04停牌
A5: 2026-08-17 | B5: 周一 | C5: 是 | D5: 09:30-15:00 | E5: T日可用(卖出T+1到账前先用余额) | F5: 客户确认净转出5万；P01当日买入批次解冻；调仓首个可执行日
A6: 2026-08-18 | B6: 周二 | C6: 是 | D6: 09:30-15:00 | E6: T+1资金可用 | F6: 周一卖出资金今日可用于再投资/划转；后手执行窗口
A7: 2026-08-19 | B7: 周三 | C7: 是 | D7: 09:30-15:00 | E7: 可用 | F7: P02若仍跌停，继续后手；压力复核
A8: 2026-08-21 | B8: 周五 | C8: 是 | D8: 09:30-15:00 | E8: 可用 | F8: 首周调仓达标复核截止
A9: 2026-08-24 | B9: 周一 | C9: 是 | D9: 09:30-15:00 | E9: 可用 | F9: 次周复核；若仍超限按规则补减
A11: 注：周末/节假日顺延到下一交易日；具体复牌日未确定，P04相关动作均为‘复牌后’。

Sheet 交易明细
A1: 交易明细：主方案整手卖出、费用、净回笼、扣费后实现盈亏
A3: 主方案（不依赖跌停P02；P04停牌不可卖）
A4: 标的 | B4: 卖出数量 | C4: 成交价(RMB) | D4: 成交额 | E4: 佣金 | F4: 印花税 | G4: 港股费用 | H4: 费用合计 | I4: 净回笼 | J4: 单位成本 | K4: 实现盈亏(扣费后)
A5: P01 | B5: 5000 | C5: 32.8 | D5: =B5*C5 -> 164000 | E5: =MAX(D5*0.0003,5) -> 49.2 | F5: =D5*0.0005 -> 82 | G5: 0 | H5: =E5+F5+G5 -> 131.2 | I5: =D5-H5 -> 163868.8 | J5: 39.23 | K5: =B5*(C5-J5)-H5 -> -32281.2
A6: P05 | B6: 200 | C6: 105 | D6: =B6*C6 -> 21000 | E6: =MAX(D6*0.0003,5) -> 6.3 | F6: =D6*0.0005 -> 10.5 | G6: 0 | H6: =E6+F6+G6 -> 16.8 | I6: =D6-H6 -> 20983.2 | J6: 82.4 | K6: =B6*(C6-J6)-H6 -> 4503.2
A7: P07 | B7: 8000 | C7: 14.076 | D7: =B7*C7 -> 112608 | E7: 0 | F7: 0 | G7: =D7*0.001 -> 112.608 | H7: =E7+F7+G7 -> 112.608 | I7: =D7-H7 -> 112495.39 | J7: 15.088 | K7: =B7*(C7-J7)-H7 -> -8208.608
A8: 合计 | D8: =SUM(D5:D7) -> 297608 | E8: =SUM(E5:E7) -> 55.5 | F8: =SUM(F5:F7) -> 92.5 | G8: =SUM(G5:G7) -> 112.608 | H8: =SUM(H5:H7) -> 260.608 | I8: =SUM(I5:I7) -> 297347.39 | K8: =SUM(K5:K7) -> -35986.608
A10: 交易后剩余持仓与组合指标
A11: 标的 | B11: 剩余数量 | C11: 现价(RMB) | D11: 剩余市值(RMB)
A12: P01 | B12: 0 | C12: 32.8 | D12: =B12*C12 -> 0
A13: P02 | B13: 3000 | C13: 58.4 | D13: =B13*C13 -> 175200
A14: P03 | B14: 8000 | C14: 9.62 | D14: =B14*C14 -> 76960
A15: P04 | B15: 6000 | C15: 12.35 | D15: =B15*C15 -> 74100
A16: P05 | B16: 1800 | C16: 105 | D16: =B16*C16 -> 189000
A17: P06 | B17: 10000 | C17: 2.88 | D17: =B17*C17 -> 28800
A18: P07 | B18: 2000 | C18: 14.076 | D18: =B18*C18 -> 28152
A19: 证券市值合计 | D19: =SUM(D12:D18) -> 572212
A21: 划出后(未交易)RMB现金 | B21: =142500-50000 -> 92500
A22: 卖出净回笼合计 | B22: =I8 -> 297347.39
A23: 交易后RMB现金 | B23: =B21+B22 -> 389847.39
A24: USD现金折算 | B24: =3000*7.18 -> 21540
A25: 交易后证券市值 | B25: =D19 -> 572212
A26: 待扣费用 | B26: =1200 -> 1200
A27: 交易后NAV | B27: =B25+B23+B24-B26 -> 982399.39
A28: P05权重 | B28: =D16/B27 -> 0.19238611
A29: 科技权重(P01+P02+P05+P07) | B29: =(D12+D13+D16+D18)/B27 -> 0.39938135
A30: 高风险权重(P01+P02+P05) | B30: =(D12+D13+D16)/B27 -> 0.37072499
A31: 外币权重(P07+USD) | B31: =(D18+B24)/B27 -> 0.050582279
A32: RMB现金权重 | B32: =B23/B27 -> 0.39683187

Sheet 资金转出影响
A1: 5万元净转出对现金与风险约束的影响（as-of → 8/17划出后）
A3: 项目 | B3: 转出前(8/14) | C3: 划出后未交易(8/17) | D3: 主方案交易后
A4: RMB现金(元) | B4: =持仓勾稽!B4 -> 142500 | C4: =B4-50000 -> 92500 | D4: =交易明细!B23 -> 389847.39
A5: USD现金折算(元) | B5: =3000*7.18 -> 21540 | C5: =3000*7.18 -> 21540 | D5: =交易明细!B24 -> 21540
A6: 证券市值(元) | B6: =持仓勾稽!J20 -> 869820 | C6: =持仓勾稽!J20 -> 869820 | D6: =交易明细!B25 -> 572212
A7: 待扣费用(元) | B7: =持仓勾稽!B7 -> 1200 | C7: =持仓勾稽!B7 -> 1200 | D7: =交易明细!B26 -> 1200
A8: 账户净资产(元) | B8: =持仓勾稽!B8 -> 1032660 | C8: =C4+C5+C6-C7 -> 982660 | D8: =交易明细!B27 -> 982399.39
A9: RMB现金占净资产 | B9: =B4/B8 -> 0.13799314 | C9: =C4/C8 -> 0.094132253 | D9: =D4/D8 -> 0.39683187
A10: 是否满足现金≥10%(划出后) | B10: — | C10: =IF(C9>=0.1,"达标","不达标") -> 不达标 | D10: =IF(D9>=0.1,"达标","达标") -> 达标
A11: 结论：转出5万使RMB现金占比由13.8%降至9.4%，跌破10%下限；必须在周一卖出变现补足，主方案卖出后RMB现金回升至约39.7%（同时压降科技与外币）。

Sheet 硬约束状态
A1: 硬约束逐条判定：阈值/当前值/反解达标量/交易后值/判定
A3: 约束名 | B3: 题面阈值 | C3: 当前值(划出后未交易) | D3: 达标所需反解值 | E3: 主方案交易后值 | F3: 偏好方案值 | G3: 判定 | H3: 绑定/已消 | I3: 相邻一手检验 | J3: 规则号
A4: 单票≤20% (P05) | B4: 20% | C4: =210000/(142500-50000+3000*7.18+869820-1200) -> 0.21370566 | D4: P05减至≤189,000：卖200股(2手)；少卖1手(100股)P05=20.31%仍超 | E4: =交易明细!B28 -> 0.19238611 | F4: 坚持不卖P05=21.4%，单票与科技同时超限 | G4: 达标 | H4: 已被R01消掉 | I4: 少卖100股P05→P05 20.31%、科技41.01%，回超 | J4: R01/R02
A5: 科技主题≤40% | B5: 40% | C5: =(164000+175200+210000+140760)/(142500-50000+3000*7.18+869820-1200) -> 0.70213502 | D5: 科技由689,960压至≤约393,500：卖P01全部5000+P05 200+P07 8000 | E5: =交易明细!B29 -> 0.39938135 | F5: 不调仓=70.2%，远超40% | G5: 达标 | H5: 当前最紧约束(技术)=约40.0% | I5: P01少卖100股→科技40.27%；P07少卖500份→40.65% | J5: R01
A6: 高风险等级≤45% | B6: 45% | C6: =(164000+175200+210000)/(142500-50000+3000*7.18+869820-1200) -> 0.55889117 | D6: 高风险由549,200压至≤约442,000；随R01同步完成 | E6: =交易明细!B30 -> 0.37072499 | F6: 不调仓=55.9% | G6: 达标 | H6: 随科技约束一并消掉 | I6: 交易后37.1%，余量约8个百分点 | J6: R01
A7: 外币≤15%(含USD现金) | B7: 15% | C7: =(140760+3000*7.18)/(142500-50000+3000*7.18+869820-1200) -> 0.16516394 | D7: 外币(P07+USD)由162,300压至≤约147,000：卖P07至≤2,000份 | E7: =交易明细!B31 -> 0.050582279 | F7: 不调仓=16.5% | G7: 达标 | H7: 随R01消掉 | I7: 交易后5.1%；USD现金21,540不可单方消除 | J7: R01
A8: RMB现金≥10%(划出后) | B8: 10% | C8: =92500/(142500-50000+3000*7.18+869820-1200) -> 0.094132253 | D8: 划出后RMB现金仅92,500(9.4%)，须卖出变现补足至≥约98,300 | E8: =交易明细!B32 -> 0.39683187 | F8: 不调仓=9.4%，不达标 | G8: 达标 | H8: 随卖出同步解决 | I8: 交易后39.7%，流动性充裕 | J8: R01/R06

Sheet 方案对比
A1: 方案对比：未调整 / PM偏好 / 合规主方案
A3: 指标 | B3: 未调整(划出后) | C3: PM偏好(不卖P05) | D3: 合规主方案 | E3: 说明
A4: P05单票权重 | B4: 21.37% | C4: 21.37% | D4: =交易明细!B28 -> 0.19238611 | E4: 偏好与未调整同样超限
A5: 科技主题权重 | B5: 70.21% | C5: ~55%* | D5: =交易明细!B29 -> 0.39938135 | E5: *偏好卖P01/P07但P05不动仍超限
A6: 高风险权重 | B6: 55.89% | C6: ~45%* | D6: =交易明细!B30 -> 0.37072499
A7: 外币权重 | B7: 16.52% | C7: ~14%* | D7: =交易明细!B31 -> 0.050582279 | E7: USD现金21,540固定
A8: RMB现金权重 | B8: 9.41% | C8: ~30%* | D8: =交易明细!B32 -> 0.39683187 | E8: 划出后须≥10%
A9: 硬约束判定 | B9: 5项中4项超限 | C9: 单票P05仍超限 | D9: 全部达标 | E9: 主方案为唯一同时满足全部硬约束的可执行路径
A10: 卖出总额(元) | B10: 0 | C10: ~30万 | D10: =交易明细!D8 -> 297608 | E10: 主方案含费用约261元
A11: * PM偏好‘P05长期看好暂不减持’未经客户批准、无风险例外审批，不能替代单票20%与科技40%上限；本表仅作对照，不作为执行依据。

Sheet 情景与压力
A1: 情景与压力（后调仓组合；客户目标：控制回撤）
A3: 组合构成(交易后)：证券572,212 / RMB现金389,847 / USD折算21,540；科技392,352、非科技证券179,860。
A4: 情景 | B4: 冲击假设 | C4: 逐日/一次性 | D4: 损失额(元) | E4: 损失率(后) | F4: 损失率(未调仓对照) | G4: 最不利
A5: 上行 | B5: 证券+8% | C5: 一次性 | D5: 45776.96 | E5: =D5/982399 -> 0.046597116 | F5: =869820*0.08/982660 -> 0.070813506 | G5: 否
A6: 横盘 | B6: 0 | C6: — | D6: 0 | E6: 0 | F6: 0 | G6: 否
A7: 市场普跌 | B7: 全部证券-10% | C7: 首日 | D7: 57221.2 | E7: =D7/982399 -> 0.058246395 | F7: =869820*0.1/982660 -> 0.088516883 | G7: 否
A8: 科技领跌 | B8: 科技-15%、其余证券-5% | C8: 首日(逐日未给定义) | D8: 67845.8 | E8: =D8/982399 -> 0.069061349 | F8: =(689960*0.15+179860*0.05)/982660 -> 0.11447194 | G8: 是
A9: 结论：最不利为‘科技领跌’情景，后调仓损失约6.9%（约6.8万），未调仓约11.5%（约11.2万）；调仓将尾部损失压低约4.6个百分点，与‘控制回撤’目标一致。
A11: 执行情景：①P01/P05/P07周一正常成交→按R01；②P02继续跌停→主方案不依赖，无需动作；③P01或P07部分未成交→当日未成交量按R03/R02次日补，并按缺口重算权重，未补满不得记‘已合规’。

Sheet 条件规则
A1: if→then 交易纪律（可执行；未成交后手单列）
A3: 规则号 | B3: 触发条件(阈值+截止时点) | C3: 方向自检 | D3: 动作 | E3: 数量及口径(基准持仓) | F3: 目标权重 | G3: 预计费用/净回笼 | H3: 执行时点 | I3: 未成交后手 | J3: 交易后复核
A4: R01 | B4: 8/17划出5万后，任一触发：P05>20% 或 科技>40% 或 RMB现金<10% | C4: 卖出科技使权重↓、现金↑，方向正确 | D4: 限价卖出P01/P05/P07 | E4: P01 5000+P05 200+P07 8000；累计总卖出量，基准=划出后持仓 | F4: 单票≤20%/科技≤40%/现金≥10% | G4: 费用≈261，净回笼≈297,347 | H4: 8/17 09:30后，以对手价附近限价挂单 | I4: 未成交量不记已成交，转R02/R03 | J4: 当日收盘后核对交易明细B28:B32
A5: R02 | B5: R01后P05仍>20%(如P01未卖完) | C5: P05权重仍超，需再减 | D5: 追加卖出P05 | E5: 按(当前P05市值−0.195×NAV)/105向上取整手；本阶段追加量 | F5: P05≤19.5% | G5: 按0.08%费率估 | H5: 8/17盘中至8/18 | I5: 若跌停则次日再挂，不追 | J5: P05权重≤19.5%
A6: R03 | B6: P01/P07订单未全额成交且科技仍>40% | C6: 科技未达标，须继续减科技 | D6: 次日补卖；若P02已打开买盘可用P02替代 | E6: 缺口整手反解；本阶段追加量 | F6: 科技≤40% | G6: 同费率 | H6: 8/18开盘 | I6: P02仍跌停封单则不用P02，改补P05 | J6: 科技≤40%
A7: R04 | B7: P04仍停牌/无买盘 | C7: 停牌不可卖 | D7: 不挂单、不计入达标 | E7: 0 | F7: — | G7: 0 | H7: — | I7: 复牌前不操作 | J7: 复牌后重估，属工业/中风险，不主动减
A8: R05 | B8: 8/17开盘前P01的8/14买入1000股 | C8: T+1前不可卖 | D8: 不把当日买入计入可卖 | E8: 8/17起P01可卖=5000 | F8: — | G8: — | H8: 8/17起 | I8: — | J8: 可卖台账=4000+1000
A9: R06 | B9: 任一复核时点RMB现金<10% | C9: 流动性不足 | D9: 暂停一切买入/回补/做T；先卖后持 | E9: 以卖出变现补足 | F9: RMB现金≥10% | G9: — | H9: 持续 | I9: 有新增出款时重算 | J9: 现金占比≥10%
A10: R07 | B10: 交易后科技因上涨重新>40%(上涨使权重恶化) | C10: 价格上涨抬高科技占比，方向自检成立 | D10: 按超出部分整手减科技 | E10: (当前科技市值−0.39×NAV)/科技均价向上整手；追加量 | F10: 科技≤39% | G10: — | H10: 出现即执行 | I10: 若涨跌停转R03 | J10: 科技回到≤39%
A11: R08 | B11: 8/21收盘前复核；未达标 | C11: 到期窗口 | D11: 按缺口在8/24补减 | E11: 整手反解；追加量 | F11: 全部5条达标 | G11: — | H11: 8/24 | I11: 仍受限则挂牌监控并书面提示 | J11: 8/24收盘后再核

Sheet 假设与缺失
A1: 假设、口径与缺失清单
A3: 条目 | B3: 类型 | C3: 来源/依据 | D3: 影响哪些结论 | E3: 补齐后需重算什么
A4: 采用托管总资产1,032,660为主口径 | B4: 已确认事实 | C4: 明细逐项勾稽：869,820+142,500+21,540−1,200 | D4: 全部权重与约束判定 | E4: —
A5: PM手工总资产1,029,000差3,660元未决 | B5: 仍缺证据 | C5: 附件未给差异来源 | D5: 权重绝对值；相对判定不变 | E5: 取得PM底稿后重算分母与各权重
A6: P06成本已重建为2.30(3.10−0.80分红) | B6: 合理推断 | C6: 文档第四节；除息参考价2.88 | D6: P06浮盈由-2,200改为+5,800 | E6: 若分红未到账则回退
A7: P01单位成本用加权平均39.23 | B7: 合理推断 | C7: 三批次数量加权 | D7: P01实现盈亏 | E7: 改用先进先出法时重算实现盈亏
A8: P07卖出按人民币净回笼、外币资产同步下降 | B8: 合理推断/待确认 | C8: 账户仅有USD现金无HKD现金记录 | D8: 外币约束与现金回升 | E8: 若实际为HKD到账，外币下降幅度与现金口径需重算
A9: P04市值用8/13价12.35 | B9: 已确认事实 | C9: 8/14全天停牌 | D9: 权重为近似，复牌后重估 | E9: 复牌价确定后重算
A10: P02跌停，主方案不依赖其成交 | B10: 已确认事实 | C10: 8/14收盘封单 | D10: 方案可执行性 | E10: P02打开后可作R03替代
A11: 无完整相关系数矩阵，风险贡献仅按波动率加权近似 | B11: 仍缺证据 | C11: 仅提供与P05相关系数 | D11: 尾部风险定性，不作精确CVaR | E11: 取得全协方差后补风险贡献分解
A12: 6个月无目标收益/止损线，情景为示意 | B12: 仍缺证据 | C12: 客户仅给‘控回撤+流动性’ | D12: 压力档选择 | E12: 客户给出回撤预算后重定阈值
A13: 本稿仅调仓前分析，未下单 | B13: 已确认事实 | C13: 文档末段 | D13: — | E13: —

Sheet 核验
A1: 核验表：关键指标公式与重算（LibreOffice 重算后填值）
A3: 被核验指标 | B3: 取值所在单元格 | C3: 公式原文 | D3: 重算值 | E3: 与正文一致
A4: 证券市值合计 | B4: 持仓勾稽!J20 | C4: SUM(J13:J19) | D4: =持仓勾稽!J20 -> 869820 | E4: 是(应=869,820)
A5: 资产重算=托管NAV | B5: 持仓勾稽!B24 | C5: B4+B5*B6+J20-B7 | D5: =持仓勾稽!B24 -> 1032660 | E5: 是(应=1,032,660)
A6: 两口径差额 | B6: 持仓勾稽!B25 | C6: B8-B9 | D6: =持仓勾稽!B25 -> 3660 | E6: 是(应=3,660)
A7: 交易后NAV | B7: 交易明细!B27 | C7: B25+B23+B24-B26 | D7: =交易明细!B27 -> 982399.39 | E7: 是(应≈982,399)
A8: P05交易后权重 | B8: 交易明细!B28 | C8: D16/B27 | D8: =交易明细!B28 -> 0.19238611 | E8: 是(应≈19.24%)
A9: 科技交易后权重 | B9: 交易明细!B29 | C9: (D12+D13+D16+D18)/B27 | D9: =交易明细!B29 -> 0.39938135 | E9: 是(应≈39.94%)
A10: 高风险交易后权重 | B10: 交易明细!B30 | C10: (D12+D13+D16)/B27 | D10: =交易明细!B30 -> 0.37072499 | E10: 是(应≈37.07%)
A11: 外币交易后权重 | B11: 交易明细!B31 | C11: (D18+B24)/B27 | D11: =交易明细!B31 -> 0.050582279 | E11: 是(应≈5.06%)
A12: RMB现金交易后权重 | B12: 交易明细!B32 | C12: B23/B27 | D12: =交易明细!B32 -> 0.39683187 | E12: 是(应≈39.68%)
A13: 卖出费用合计 | B13: 交易明细!H8 | C13: SUM(H5:H7) | D13: =交易明细!H8 -> 260.608 | E13: 是(应≈260.6)
A14: 净回笼合计 | B14: 交易明细!I8 | C14: SUM(I5:I7) | D14: =交易明细!I8 -> 297347.39 | E14: 是(应≈297,347)
A15: P01费用隐含费率 | B15: 交易明细!H5/D5 | C15: H5/D5 | D15: =交易明细!H5/交易明细!D5 -> 0.0008 | E15: 是(应=0.08%：佣金0.03%+印花0.05%)

Sheet 交付自检回执
A1: 交付自检回执（逐行填值）
A3: 自检项 | B3: 填写值
A4: 交付清单 | B4: 组合持仓诊断与交易纪律.xlsx
A5: 主工件位置 | B5: 本工作簿全部工作表；决策结论见‘硬约束状态’‘条件规则’
A6: 工作簿可复算 | B6: ‘核验’表
A7: 占比分母 | B7: 分母=交易后NAV≈982,399(主口径托管1,032,660−50,000−费用261)；权重=个股市值/NAV
A8: 最紧约束 | B8: 科技主题 / 当前70.21% / 阈值40% / 反解：卖P01 5000+P05 200+P07 8000 / 规则R01；软偏好冲突=PM不卖P05
A9: 分解型占比加总 | B9: 个股权重合计=证券占比84.2%+现金15.9%−待扣费用0.1%=100%；科技/高风险/外币各自为子集不强行加总
A10: 最不利情景 | B10: 科技领跌 / 后调仓损失≈6.9% / 未调仓≈11.5%，均高于0但较前下降
A11: 日期来源 | B11: 行动日8/17、复核日8/21、补减日8/24均取自‘交易日历’表
A12: 数量口径 | B12: R01为累计总卖出量，基准=划出后持仓；R02/R03/R07为阶段追加量
A13: 费用口径 | B13: P01/P05=佣金0.03%(最低5)+印花0.05%；P07=0.10%；隐含费率P01=0.08%，与费率表一致
A14: 跨文件一致 | B14: 抽查：交易后NAV 交易明细!B27 ≈ 资金转出影响!D8 ≈ 情景表基准；P05权重 交易明细!B28 = 硬约束状态E4
