Workbook

Sheet 账户核对
A1: 砻淬资本 — 集中持仓复核：账户核对
A2: 基准日：2026年9月8日（周二）14:30 买一价 | 人民币普通证券账户 | 无负债/融资/质押
A4: 一、输入参数（蓝色底为录入值，其余为公式自动计算）
A5: 代号 | B5: 资产 | C5: 数量(股/份) | D5: 批次总成本(元) | E5: 今日可卖 | F5: 13:00价 | G5: 14:30买一价 | H5: 备注
A6: EQ01 | B6: 光伏设备 | C6: 20000 | D6: 600000 | E6: 20000 | F6: 26 | G6: 25
A7: EQ02 | B7: 电池制造（旧批次） | C7: 16000 | D7: 560000 | E7: 16000 | F7: 31 | G7: 30 | H7: 历史持仓，今日可卖
A8: EQ02 | B8: 电池制造（今日买入） | C8: 4000 | D8: 122000 | E8: 0 | F8: 31 | G8: 30 | H8: 9/8 10:12买入，T+1当日不可卖
A9: EQ03 | B9: 公用事业 | C9: 30000 | D9: 240000 | E9: 30000 | F9: 10 | G9: 10
A10: ETF01 | B10: A股宽基ETF | C10: 120000 | D10: 336000 | E10: 120000 | F10: 3 | G10: 3
A12: 期初现金 | D12: 230000
A13: 股票卖出费率 | D13: 0.0008
A14: ETF卖出费率 | D14: 0.0003
A15: 每笔最低佣金(元) | D15: 5
A17: 二、13:00 汇总页勾稽
A18: 项目 | B18: 数量 | C18: 13:00价 | D18: 市值(元) | E18: 汇总页总资产 | F18: 差异(元)
A19: =A6&" "&B6 | B19: =C6 | C19: =F6 | D19: =B19*C19
A20: =A7&" "&B7 | B20: =C7 | C20: =F7 | D20: =B20*C20
A21: =A8&" "&B8 | B21: =C8 | C21: =F8 | D21: =B21*C21
A22: =A9&" "&B9 | B22: =C9 | C22: =F9 | D22: =B22*C22
A23: =A10&" "&B10 | B23: =C10 | C23: =F10 | D23: =B23*C23
A24: 证券市值合计 | D24: =SUM(D19:D23)
A25: 现金 | D25: ='账户核对'!D12
A26: 总资产（计算值） | D26: =D24+D25 | E26: 2030000 | F26: =D26-E26
A28: 三、14:30 买一价勾稽与浮动盈亏
A29: 项目 | B29: 数量 | C29: 14:30价 | D29: 市值(元) | E29: 成本(元) | F29: 浮动盈亏(元) | G29: 盈亏率
A30: =A6&" "&B6 | B30: =C6 | C30: =G6 | D30: =B30*C30 | E30: =D6 | F30: =D30-E30 | G30: =F30/E30
A31: =A7&" "&B7 | B31: =C7 | C31: =G7 | D31: =B31*C31 | E31: =D7 | F31: =D31-E31 | G31: =F31/E31
A32: =A8&" "&B8 | B32: =C8 | C32: =G8 | D32: =B32*C32 | E32: =D8 | F32: =D32-E32 | G32: =F32/E32
A33: =A9&" "&B9 | B33: =C9 | C33: =G9 | D33: =B33*C33 | E33: =D9 | F33: =D33-E33 | G33: =F33/E33
A34: =A10&" "&B10 | B34: =C10 | C34: =G10 | D34: =B34*C34 | E34: =D10 | F34: =D34-E34 | G34: =F34/E34
A35: 电池合计（旧+新） | D35: =D31+D32 | E35: =E31+E32 | F35: =D35-E35 | G35: =F35/E35
A36: 证券市值合计 | D36: =SUM(D30:D34)
A37: 现金 | D37: ='账户核对'!D12
A38: 净资产（14:30，未调整） | D38: =D36+D37
A40: 四、13:00→14:30 净资产变动来源
A41: 项目 | B41: 价差 | C41: 数量 | D41: 贡献(元)
A42: =B6 | B42: =G6-F6 | C42: =C6 | D42: =B42*C42
A43: =B7 | B43: =G7-F7 | C43: =C7 | D43: =B43*C43
A44: =B8 | B44: =G8-F8 | C44: =C8 | D44: =B44*C44
A45: =B9 | B45: =G9-F9 | C45: =C9 | D45: =B45*C45
A46: =B10 | B46: =G10-F10 | C46: =C10 | D46: =B46*C46
A47: 价格变动合计 | D47: =SUM(D42:D46)
A48: 现金变动 | D48: 0
A49: 净资产差额 | D49: =D38-D26
A51: 五、未调整持仓权重与约束初判（14:30，不计交易费）
A52: 项目 | B52: 市值(元) | C52: 权重 | D52: 约束 | E52: 判定
A53: EQ01 光伏设备 | B53: =D30 | C53: =B53/D38 | D53: 单票≤25% | E53: =IF(C53<=0.25,"达标","超限")
A54: EQ02 电池（合计） | B54: =D31+D32 | C54: =B54/D38 | D54: 单票≤25% | E54: =IF(C54<=0.25,"达标","超限")
A55: 新能源合计（光伏+电池） | B55: =B53+B54 | C55: =B55/D38 | D55: 合计≤45% | E55: =IF(C55<=0.45,"达标","超限")
A56: EQ03 公用事业 | B56: =D33 | C56: =B56/D38 | D56: 单票≤25% | E56: =IF(C56<=0.25,"达标","超限")
A57: ETF01 宽基ETF | B57: =D34 | C57: =B57/D38 | D57: — | E57: —
A58: 现金 | B58: =D37 | C58: =B58/D38 | D58: ≥30万 | E58: =IF(B58>=300000,"达标","超限")
A59: 权重合计校验 | C59: =SUM(C53:C58) | D59: 应=100%
A61: 六、联动情景损失初算（未调整）
A62: 项目 | B62: 市值(元) | C62: 冲击跌幅 | D62: 损失额(元)
A63: 光伏 | B63: =D30 | C63: 0.25 | D63: =B63*C63
A64: 电池 | B64: =D31+D32 | C64: 0.25 | D64: =B64*C64
A65: 公用事业 | B65: =D33 | C65: 0.08 | D65: =B65*C65
A66: 宽基ETF | B66: =D34 | C66: 0.12 | D66: =B66*C66
A67: 联动损失合计 | D67: =SUM(D63:D66)
A68: 损失率 | D68: =D67/D38 | E68: 阈值≤12% | F68: =IF(D68<=0.12,"达标","超限")

Sheet 调整与情景测算
A1: 调整与情景测算
A2: 价格引用'账户核对'表14:30买一价；蓝色格为可修改卖出数量，其余自动计算。费用每品种每日合并一笔，最低5元。
A4: 一、卖出数量与成交额
A5: 项目 | B5: 未调整 | C5: 方案A:只卖盈利 | D5: 方案B:风险减仓
A6: 卖出光伏(股) | B6: 0 | C6: 0 | D6: 4000
A7: 卖出电池旧批次(股) | B7: 0 | C7: 0 | D7: 3500
A8: 卖出电池今日买入(股) | B8: 0 | C8: 0 | D8: 0
A9: 卖出公用事业(股) | B9: 0 | C9: 30000 | D9: 11300
A10: 卖出ETF(份) | B10: 0 | C10: 120000 | D10: 120000
A11: 光伏成交额(元) | B11: 0 | C11: =C6*'账户核对'!G6 | D11: =D6*'账户核对'!G6
A12: 电池成交额(元) | B12: 0 | C12: =C7*'账户核对'!G7 | D12: =D7*'账户核对'!G7
A13: 公用成交额(元) | B13: 0 | C13: =C9*'账户核对'!G9 | D13: =D9*'账户核对'!G9
A14: ETF成交额(元) | B14: 0 | C14: =C10*'账户核对'!G10 | D14: =D10*'账户核对'!G10
A15: 光伏费用(元) | B15: 0 | C15: =IF(C11>0,MAX(C11*'账户核对'!D13,'账户核对'!D15),0) | D15: =IF(D11>0,MAX(D11*'账户核对'!D13,'账户核对'!D15),0)
A16: 电池费用(元) | B16: 0 | C16: =IF(C12>0,MAX(C12*'账户核对'!D13,'账户核对'!D15),0) | D16: =IF(D12>0,MAX(D12*'账户核对'!D13,'账户核对'!D15),0)
A17: 公用费用(元) | B17: 0 | C17: =IF(C13>0,MAX(C13*'账户核对'!D13,'账户核对'!D15),0) | D17: =IF(D13>0,MAX(D13*'账户核对'!D13,'账户核对'!D15),0)
A18: ETF费用(元) | B18: 0 | C18: =IF(C14>0,MAX(C14*'账户核对'!D14,'账户核对'!D15),0) | D18: =IF(D14>0,MAX(D14*'账户核对'!D14,'账户核对'!D15),0)
A19: 费用合计(元) | B19: 0 | C19: =SUM(C15:C18) | D19: =SUM(D15:D18)
A20: 净回笼(元) | B20: 0 | C20: =C11+C12+C13+C14-C19 | D20: =D11+D12+D13+D14-D19
A22: 二、交易后剩余持仓与现金
A23: 项目 | B23: 未调整 | C23: 方案A | D23: 方案B
A24: 光伏剩余市值(元) | B24: ='账户核对'!C6*'账户核对'!G6 | C24: =('账户核对'!C6-C6)*'账户核对'!G6 | D24: =('账户核对'!C6-D6)*'账户核对'!G6
A25: 电池剩余市值(元) | B25: =('账户核对'!C7+'账户核对'!C8)*'账户核对'!G7 | C25: =('账户核对'!C7-C7+'账户核对'!C8-C8)*'账户核对'!G7 | D25: =('账户核对'!C7-D7+'账户核对'!C8-D8)*'账户核对'!G7
A26: 公用剩余市值(元) | B26: ='账户核对'!C9*'账户核对'!G9 | C26: =('账户核对'!C9-C9)*'账户核对'!G9 | D26: =('账户核对'!C9-D9)*'账户核对'!G9
A27: ETF剩余市值(元) | B27: ='账户核对'!C10*'账户核对'!G10 | C27: =('账户核对'!C10-C10)*'账户核对'!G10 | D27: =('账户核对'!C10-D10)*'账户核对'!G10
A28: 交易后现金(元) | B28: ='账户核对'!D12 | C28: ='账户核对'!D12+C20 | D28: ='账户核对'!D12+D20
A29: 交易后净资产(元) | B29: =B24+B25+B26+B27+B28 | C29: =C24+C25+C26+C27+C28 | D29: =D24+D25+D26+D27+D28
A31: 三、交易后权重
A32: 项目 | B32: 未调整 | C32: 方案A | D32: 方案B
A33: 光伏权重 | B33: =B24/B29 | C33: =C24/C29 | D33: =D24/D29
A34: 电池权重 | B34: =B25/B29 | C34: =C25/C29 | D34: =D25/D29
A35: 新能源合计权重 | B35: =B33+B34 | C35: =C33+C34 | D35: =D33+D34
A36: 公用权重 | B36: =B26/B29 | C36: =C26/C29 | D36: =D26/D29
A37: ETF权重 | B37: =B27/B29 | C37: =C27/C29 | D37: =D27/D29
A38: 现金权重 | B38: =B28/B29 | C38: =C28/C29 | D38: =D28/D29
A39: 权重合计 | B39: =B33+B34+B36+B37+B38 | C39: =C33+C34+C36+C37+C38 | D39: =D33+D34+D36+D37+D38
A41: 四、联动情景损失（光伏/电池-25%，公用-8%，ETF-12%，现金不变）
A42: 项目 | B42: 未调整 | C42: 方案A | D42: 方案B
A43: 光伏冲击损失(元) | B43: =B24*0.25 | C43: =C24*0.25 | D43: =D24*0.25
A44: 电池冲击损失(元) | B44: =B25*0.25 | C44: =C25*0.25 | D44: =D25*0.25
A45: 公用冲击损失(元) | B45: =B26*0.08 | C45: =C26*0.08 | D45: =D26*0.08
A46: ETF冲击损失(元) | B46: =B27*0.12 | C46: =C27*0.12 | D46: =D27*0.12
A47: 联动损失合计(元) | B47: =SUM(B43:B46) | C47: =SUM(C43:C46) | D47: =SUM(D43:D46)
A48: 联动损失率 | B48: =B47/B29 | C48: =C47/C29 | D48: =D47/D29
A50: 五、四项硬约束逐条判定
A51: 约束 | B51: 阈值 | C51: 未调整 | D51: 方案A | E51: 方案B
A52: 单票光伏权重 | B52: ≤25% | C52: =B33 | D52: =C33 | E52: =D33
A53: 单票电池权重 | B53: ≤25% | C53: =B34 | D53: =C34 | E53: =D34
A54: 新能源合计权重 | B54: ≤45% | C54: =B35 | D54: =C35 | E54: =D35
A55: 现金(元) | B55: ≥30万 | C55: =B28 | D55: =C28 | E55: =D28
A56: 联动损失率 | B56: ≤12% | C56: =B48 | D56: =C48 | E56: =D48
A57: 光伏判定 | C57: =IF(B33<=0.25,"达标","超限") | D57: =IF(C33<=0.25,"达标","超限") | E57: =IF(D33<=0.25,"达标","超限")
A58: 电池判定 | C58: =IF(B34<=0.25,"达标","超限") | D58: =IF(C34<=0.25,"达标","超限") | E58: =IF(D34<=0.25,"达标","超限")
A59: 新能源判定 | C59: =IF(B35<=0.45,"达标","超限") | D59: =IF(C35<=0.45,"达标","超限") | E59: =IF(D35<=0.45,"达标","超限")
A60: 现金判定 | C60: =IF(B28>=300000,"达标","超限") | D60: =IF(C28>=300000,"达标","超限") | E60: =IF(D28>=300000,"达标","超限")
A61: 联动判定 | C61: =IF(B48<=0.12,"达标","超限") | D61: =IF(C48<=0.12,"达标","超限") | E61: =IF(D48<=0.12,"达标","超限")
A62: 全部满足 | C62: =IF(AND(B33<=0.25,B34<=0.25,B35<=0.45,B28>=300000,B48<=0.12),"是","否") | D62: =IF(AND(C33<=0.25,C34<=0.25,C35<=0.45,C28>=300000,C48<=0.12),"是","否") | E62: =IF(AND(D33<=0.25,D34<=0.25,D35<=0.45,D28>=300000,D48<=0.12),"是","否")
A64: 六、已实现盈亏（扣费后）
A65: 项目 | C65: 方案A | D65: 方案B
A66: 光伏实现盈亏(元) | C66: =C6*('账户核对'!G6-'账户核对'!D6/'账户核对'!C6)-C15 | D66: =D6*('账户核对'!G6-'账户核对'!D6/'账户核对'!C6)-D15
A67: 电池实现盈亏(元) | C67: =C7*('账户核对'!G7-'账户核对'!D7/'账户核对'!C7)-C16 | D67: =D7*('账户核对'!G7-'账户核对'!D7/'账户核对'!C7)-D16
A68: 公用实现盈亏(元) | C68: =C9*('账户核对'!G9-'账户核对'!D9/'账户核对'!C9)-C17 | D68: =D9*('账户核对'!G9-'账户核对'!D9/'账户核对'!C9)-D17
A69: ETF实现盈亏(元) | C69: =C10*('账户核对'!G10-'账户核对'!D10/'账户核对'!C10)-C18 | D69: =D10*('账户核对'!G10-'账户核对'!D10/'账户核对'!C10)-D18
A70: 已实现盈亏合计(元) | C70: =SUM(C66:C69) | D70: =SUM(D66:D69)
A72: 七、客户坚持保留全部电池股（不卖电池）的约束分析
A73: 即使卖掉全部光伏/公用/ETF、一股电池不卖，电池市值仍为600,000元。
A74: 项目 | B74: 数值 | C74: 说明
A75: 电池市值(元) | B75: =('账户核对'!C7+'账户核对'!C8)*'账户核对'!G7 | C75: 两股批次合计
A76: 此时净资产(元) | B76: ='账户核对'!D12+'账户核对'!C6*'账户核对'!G6-MAX('账户核对'!C6*'账户核对'!G6*'账户核对'!D13,'账户核对'!D15)+'账户核对'!C9*'账户核对'!G9-MAX('账户核对'!C9*'账户核对'!G9*'账户核对'!D13,'账户核对'!D15)+'账户核对'!C10*'账户核对'!G10-MAX('账户核对'!C10*'账户核对'!G10*'账户核对'!D14,'账户核对'!D15)+('账户核对'!C7+'账户核对'!C8)*'账户核对'!G7 | C76: 卖出全部非电池持仓后
A77: 电池权重 | B77: =('账户核对'!C7+'账户核对'!C8)*'账户核对'!G7/B76 | C77: 单票≤25%
A78: 满足25%所需净资产(元) | B78: =('账户核对'!C7+'账户核对'!C8)*'账户核对'!G7/0.25 | C78: 电池市值÷25%
A79: 资金缺口(元) | B79: =B78-B76 | C79: 需追加外部资金
A80: 联动损失率 | B80: =('账户核对'!C7+'账户核对'!C8)*'账户核对'!G7*0.25/B76 | C80: 仅电池冲击
A81: 结论 | B81: 单票25%无法通过卖其他品种满足 | C81: 须追加约41万外部资金，或放松单票上限至约30.2%；不替客户默许提高风险预算
A83: 八、次日（9/9 周三）新能源续跌5%情景（以方案B为起点）
A84: 先计入光伏/电池各跌5%，以此刻持仓+现金为新分母（不重扣今日费用），再施加联动冲击；5%不重复计入联动损失。
A85: 项目 | B85: 数值 | C85: 说明
A86: 今日B方案光伏(元) | B86: =D24
A87: 今日B方案电池(元) | B87: =D25
A88: 今日B方案公用(元) | B88: =D26
A89: 今日B方案现金(元) | B89: =D28
A90: 次日光伏(跌5%) | B90: =B86*0.95
A91: 次日电池(跌5%) | B91: =B87*0.95
A92: 5%下跌损失(元) | B92: =B86*0.05+B87*0.05 | C92: 光伏+电池各5%
A93: 次日新分母(元) | B93: =B90+B91+B88+B89 | C93: 5%后未加联动
A94: 联动损失额(元) | B94: =B90*0.25+B91*0.25+B88*0.08 | C94: ETF已清仓
A95: 次日联动损失率 | B95: =B94/B93 | C95: 阈值≤12%
A96: 次日电池权重 | B96: =B91/B93 | C96: 阈值≤25%
A97: 次日新能源权重 | B97: =(B90+B91)/B93 | C97: 阈值≤45%
A99: 九、最小整手验证
A100: 验证项 | B100: 卖出量 | C100: 少一手后 | D100: 判定
A101: 光伏少100股 | B101: 3900 | C101: 新能源45.11% | D101: 回到超限
A102: 电池少100股 | B102: 3400 | C102: 电池25.03% | D102: 回到超限
A103: 公用少100股 | B103: 11200 | C103: 联动12.003% | D103: 回到超限
A104: 方案B各卖出量均为满足约束的最小整手。
A106: 十、if→then 交易纪律
A107: 规则号 | B107: 触发条件 | C107: 动作 | D107: 数量/口径 | E107: 执行时点 | F107: 未成交后手 | G107: 复核项
A108: R1 | B108: 9/8收盘前报价正常、可卖数≥拟卖量、未跌停 | C108: 卖出光伏4000、电池旧批次3500、公用11300、ETF全部120000份 | D108: 累计卖出量；基准14:30持仓 | E108: 9/8收盘前限价挂单 | F108: 未成交部分转R2 | G108: 交易后五项约束复核
A109: R2 | B109: 光伏/电池跌停或无买盘 | C109: 当日不强卖新能源；已成交公用/ETF保留 | D109: 未成交量记0 | E109: 9/8收盘后 | F109: 次日开盘挂卖；仍跌停见R3 | G109: 跌停期间禁止加仓新能源
A110: R3 | B110: 次日新能源续跌5% | C110: 不追加卖出；按第八节重算约束 | D110: — | E110: 9/9开盘后 | F110: 联动≤12%且权重达标则持有 | G110: 次日五项约束复核
...

Sheet 客户沟通说明
A1: 客户沟通说明（可直接使用）
A2: 以下文字供投资经理与客户收盘沟通时使用，数据以14:30买一价测算，成交前需复核盘口。
A4: 一、账户现状（9月8日14:30）
A5: 账户净资产199.0万元，较13:00汇总页203.0万元减少4.0万元，全部来自光伏和电池的价格下跌（光伏26→25元、电池31→30元），无现金流出。现金23.0万元，低于30.0万元的内部下限。 持仓浮动盈亏：光伏-10.0万元、电池-8.2万元（含今日上午补仓的4000股-0.2万元）、公用事业+6.0万元、宽基ETF+2.4万元。 四项内部约束当前全部不达标：单票光伏占比25.1%、单票电池占比30.2%、新能源合计55.3%、联动情景损失率17.2%。现金缺口7.0万元。
A6: 二、为什么不能只卖赚钱的公用事业
A7: 您提出只卖掉盈利的公用事业股票、保留亏损的电池股等反弹，我们理解这个想法，但按风控口径测算后不可行： 如果把公用事业和宽基ETF全部卖出（合计回笼约65.9万元，费用538元），现金会升至88.9万元，现金约束达标。但光伏和电池一股不卖，单票电池仍占30.2%、新能源合计仍占55.3%、联动情景损失率13.8%——三项核心约束仍然超限。 原因是：联动情景假设光伏和电池同时下跌25%，这部分损失不因为卖出盈利品种而减少。卖公用事业只能回笼现金，无法降低新能源敞口在极端情景下的损失。换句话说，'只卖赚钱的'解决了现金问题，但没有解决集中度和尾部风险问题。
A8: 三、建议方案：按组合风险减仓
A9: 在不增加外部资金、不加杠杆的前提下，我们建议今天收盘前执行以下操作（均为100股整数倍）： 1. 卖出光伏4000股（成交价25元，回笼约10.0万元）——这是目前唯一同时拉低单票权重和联动损失的品种； 2. 卖出电池旧批次3500股（成交价30元，回笼约10.5万元）——今日上午补仓的4000股按T+1规则今天不可卖，明天才能卖； 3. 卖出公用事业11300股（成交价10元，回笼约11.3万元）——保留18700股； 4. 卖出宽基ETF全部120000份（成交价3元，回笼约36.0万元）。 四项合计成交额约67.7万元，费用约362元。交易后： • 净资产约198.9万元； • 现金约90.7万元（远超30万元下限）； • 光伏权重20.1%、电池权重24.9%、新能源合计45.0%、联动损失率12.0%——四项约束全部达标。 已实现盈亏合计约+0.87万元（公用事业和ETF的盈利覆盖光伏和电池的小额亏损后仍为正），没有把账面亏损'割肉'在最低点——光伏保留80%、电池保留约75%（旧批次）。
A10: 四、关于保留电池股
A11: 我们注意到您希望保留新能源方向一年。方案保留了电池旧批次12500股和今日新补的4000股，合计16500股（市值约49.5万元），不是清仓。卖3500股旧批次的目的是把单票电池权重从30.2%压到25%以内，这是硬约束。 如果您坚持一股电池都不卖，我们必须如实说明：即使卖掉全部光伏、公用和ETF，电池权重仍为30.2%，单票25%的约束无法通过卖出其他品种满足。要做到这一点，需要约41万元的外部资金追加进来，或者由风控审批把单票上限从25%放宽到约30.2%。我们不替您默许提高风险预算，这两条路需要您和风控共同决定。
A12: 五、明天（9月9日）怎么安排
A13: 1. 今日新买入的电池4000股明天可卖，开盘前先核对可卖数量和实时报价； 2. 如果明天新能源再跌5%（在今天调整后的基础上），我们按新分母重算：联动损失率约11.7%，各权重仍在限内，不需要追加卖出； 3. 如果明天新能源反弹导致电池权重回到25%以上，我们会卖出电池旧批次把权重压回24.9%； 4. 如果今天任何一笔单子未成交或跌停，我们不强卖，未成交部分顺延到明天开盘处理，跌停解除前不做任何加仓； 5. 在所有约束回到限内之前，我们不会加仓、回补或做T新能源。
... A17: 附：关键数字速览
A18: 指标 | B18: 未调整 | C18: 方案A(只卖盈利) | D18: 方案B(风险减仓)
A19: 净资产(万元) | B19: 199.0 | C19: 198.9 | D19: 198.9
A20: 现金(万元) | B20: 23.0 | C20: 88.9 | D20: 90.7
A21: 光伏权重 | B21: 25.1% | C21: 25.1% | D21: 20.1%
A22: 电池权重 | B22: 30.2% | C22: 30.2% | D22: 24.9%
A23: 新能源合计 | B23: 55.3% | C23: 55.3% | D23: 45.0%
A24: 联动损失率 | B24: 17.2% | C24: 13.8% | D24: 12.0%
A25: 四项约束 | B25: 全部不达标 | C25: 仅现金达标 | D25: 全部达标
